{
 "filetype": "conformal-table",
 "data": [
  {
   "Object": "/mcs4_core_clockgen_clk1_reg/U$1",
   "Type": "DFF",
   "Mapping": "/mcs4_core_clockgen_clk1_reg/U$1",
   "Phase": "+",
   "User Setup object phase inversion": "+",
   "User Setup mapped object phase inversion": "+",
   "highlite": 0
  },
  {
   "Object": "/mcs4_core_clockgen_clk2_reg/U$1",
   "Type": "DFF",
   "Mapping": "/mcs4_core_clockgen_clk2_reg/U$1",
   "Phase": "+",
   "User Setup object phase inversion": "+",
   "User Setup mapped object phase inversion": "+",
   "highlite": 0
  },
  {
   "Object": "/mcs4_core_clockgen_clockdiv_reg[0]/U$1",
   "Type": "DFF",
   "Mapping": "/mcs4_core_clockgen_clockdiv_reg[0]/U$1",
   "Phase": "+",
   "User Setup object phase inversion": "+",
   "User Setup mapped object phase inversion": "+",
   "highlite": 0
  },
  {
   "Object": "/mcs4_core_clockgen_clockdiv_reg[1]/U$1",
   "Type": "DFF",
   "Mapping": "/mcs4_core_clockgen_clockdiv_reg[1]/U$1",
   "Phase": "+",
   "User Setup object phase inversion": "+",
   "User Setup mapped object phase inversion": "+",
   "highlite": 0
  },
  {
   "Object": "/mcs4_core_clockgen_clockdiv_reg[3]/U$1",
   "Type": "DFF",
   "Mapping": "/mcs4_core_clockgen_clockdiv_reg[3]/U$1",
   "Phase": "+",
   "User Setup object phase inversion": "+",
   "User Setup mapped object phase inversion": "+",
   "highlite": 0
  },
  {
   "Object": "/mcs4_core_clockgen_clockdiv_reg[4]/U$1",
   "Type": "DFF",
   "Mapping": "/mcs4_core_clockgen_clockdiv_reg[4]/U$1",
   "Phase": "+",
   "User Setup object phase inversion": "+",
   "User Setup mapped object phase inversion": "+",
   "highlite": 0
  },
  {
   "Object": "/mcs4_core_i4004_alu_board_acc_out_reg[0]/U$1",
   "Type": "DFF",
   "Mapping": "/mcs4_core_i4004_alu_board_acc_out_reg[0]/U$1",
   "Phase": "+",
   "User Setup object phase inversion": "+",
   "User Setup mapped object phase inversion": "+",
   "highlite": 0
  },
  {
   "Object": "/mcs4_core_i4004_alu_board_acc_out_reg[1]/U$1",
   "Type": "DFF",
   "Mapping": "/mcs4_core_i4004_alu_board_acc_out_reg[1]/U$1",
   "Phase": "+",
   "User Setup object phase inversion": "+",
   "User Setup mapped object phase inversion": "+",
   "highlite": 0
  },
  {
   "Object": "/mcs4_core_i4004_alu_board_acc_out_reg[2]/U$1",
   "Type": "DFF",
   "Mapping": "/mcs4_core_i4004_alu_board_acc_out_reg[2]/U$1",
   "Phase": "+",
   "User Setup object phase inversion": "+",
   "User Setup mapped object phase inversion": "+",
   "highlite": 0
  },
  {
   "Object": "/mcs4_core_i4004_alu_board_acc_reg[0]/U$1",
   "Type": "DFF",
   "Mapping": "/mcs4_core_i4004_alu_board_acc_reg[0]/U$1",
   "Phase": "+",
   "User Setup object phase inversion": "+",
   "User Setup mapped object phase inversion": "+",
   "highlite": 0
  },
  {
   "Object": "/mcs4_core_i4004_alu_board_acc_reg[1]/U$1",
   "Type": "DFF",
   "Mapping": "/mcs4_core_i4004_alu_board_acc_reg[1]/U$1",
   "Phase": "+",
   "User Setup object phase inversion": "+",
   "User Setup mapped object phase inversion": "+",
   "highlite": 0
  },
  {
   "Object": "/mcs4_core_i4004_alu_board_acc_reg[2]/U$1",
   "Type": "DFF",
   "Mapping": "/mcs4_core_i4004_alu_board_acc_reg[2]/U$1",
   "Phase": "+",
   "User Setup object phase inversion": "+",
   "User Setup mapped object phase inversion": "+",
   "highlite": 0
  },
  {
   "Object": "/mcs4_core_i4004_alu_board_acc_reg[3]/U$1",
   "Type": "DFF",
   "Mapping": "/mcs4_core_i4004_alu_board_acc_reg[3]/U$1",
   "Phase": "+",
   "User Setup object phase inversion": "+",
   "User Setup mapped object phase inversion": "+",
   "highlite": 0
  },
  {
   "Object": "/mcs4_core_i4004_alu_board_cy_1_reg/U$1",
   "Type": "DFF",
   "Mapping": "/mcs4_core_i4004_alu_board_cy_1_reg/U$1",
   "Phase": "+",
   "User Setup object phase inversion": "+",
   "User Setup mapped object phase inversion": "+",
   "highlite": 0
  },
  {
   "Object": "/mcs4_core_i4004_alu_board_cy_reg/U$1",
   "Type": "DFF",
   "Mapping": "/mcs4_core_i4004_alu_board_cy_reg/U$1",
   "Phase": "+",
   "User Setup object phase inversion": "+",
   "User Setup mapped object phase inversion": "+",
   "highlite": 0
  },
  {
   "Object": "/mcs4_core_i4004_alu_board_n0870_reg/U$1",
   "Type": "DFF",
   "Mapping": "/mcs4_core_i4004_alu_board_n0870_reg/U$1",
   "Phase": "+",
   "User Setup object phase inversion": "+",
   "User Setup mapped object phase inversion": "+",
   "highlite": 0
  },
  {
   "Object": "/mcs4_core_i4004_alu_board_n0871_reg/U$1",
   "Type": "DFF",
   "Mapping": "/mcs4_core_i4004_alu_board_n0871_reg/U$1",
   "Phase": "+",
   "User Setup object phase inversion": "+",
   "User Setup mapped object phase inversion": "+",
   "highlite": 0
  },
  {
   "Object": "/mcs4_core_i4004_alu_board_n0872_reg/U$1",
   "Type": "DFF",
   "Mapping": "/mcs4_core_i4004_alu_board_n0872_reg/U$1",
   "Phase": "+",
   "User Setup object phase inversion": "+",
   "User Setup mapped object phase inversion": "+",
   "highlite": 0
  },
  {
   "Object": "/mcs4_core_i4004_alu_board_n0873_reg/U$1",
   "Type": "DFF",
   "Mapping": "/mcs4_core_i4004_alu_board_n0873_reg/U$1",
   "Phase": "+",
   "User Setup object phase inversion": "+",
   "User Setup mapped object phase inversion": "+",
   "highlite": 0
  },
  {
   "Object": "/mcs4_core_i4004_alu_board_n0887_reg/U$1",
   "Type": "DFF",
   "Mapping": "/mcs4_core_i4004_alu_board_n0887_reg/U$1",
   "Phase": "+",
   "User Setup object phase inversion": "+",
   "User Setup mapped object phase inversion": "+",
   "highlite": 0
  },
  {
   "Object": "/mcs4_core_i4004_alu_board_n0889_reg/U$1",
   "Type": "DFF",
   "Mapping": "/mcs4_core_i4004_alu_board_n0889_reg/U$1",
   "Phase": "+",
   "User Setup object phase inversion": "+",
   "User Setup mapped object phase inversion": "+",
   "highlite": 0
  },
  {
   "Object": "/mcs4_core_i4004_alu_board_n0891_reg/U$1",
   "Type": "DFF",
   "Mapping": "/mcs4_core_i4004_alu_board_n0891_reg/U$1",
   "Phase": "+",
   "User Setup object phase inversion": "+",
   "User Setup mapped object phase inversion": "+",
   "highlite": 0
  },
  {
   "Object": "/mcs4_core_i4004_alu_board_n0893_reg/U$1",
   "Type": "DFF",
   "Mapping": "/mcs4_core_i4004_alu_board_n0893_reg/U$1",
   "Phase": "+",
   "User Setup object phase inversion": "+",
   "User Setup mapped object phase inversion": "+",
   "highlite": 0
  },
  {
   "Object": "/mcs4_core_i4004_alu_board_tmp_reg[0]/U$1",
   "Type": "DFF",
   "Mapping": "/mcs4_core_i4004_alu_board_tmp_reg[0]/U$1",
   "Phase": "+",
   "User Setup object phase inversion": "+",
   "User Setup mapped object phase inversion": "+",
   "highlite": 0
  },
  {
   "Object": "/mcs4_core_i4004_alu_board_tmp_reg[1]/U$1",
   "Type": "DFF",
   "Mapping": "/mcs4_core_i4004_alu_board_tmp_reg[1]/U$1",
   "Phase": "+",
   "User Setup object phase inversion": "+",
   "User Setup mapped object phase inversion": "+",
   "highlite": 0
  },
  {
   "Object": "/mcs4_core_i4004_alu_board_tmp_reg[2]/U$1",
   "Type": "DFF",
   "Mapping": "/mcs4_core_i4004_alu_board_tmp_reg[2]/U$1",
   "Phase": "+",
   "User Setup object phase inversion": "+",
   "User Setup mapped object phase inversion": "+",
   "highlite": 0
  },
  {
   "Object": "/mcs4_core_i4004_alu_board_tmp_reg[3]/U$1",
   "Type": "DFF",
   "Mapping": "/mcs4_core_i4004_alu_board_tmp_reg[3]/U$1",
   "Phase": "+",
   "User Setup object phase inversion": "+",
   "User Setup mapped object phase inversion": "+",
   "highlite": 0
  },
  {
   "Object": "/mcs4_core_i4004_id_board_n0360_reg/U$1",
   "Type": "DFF",
   "Mapping": "/mcs4_core_i4004_id_board_n0360_reg/U$1",
   "Phase": "+",
   "User Setup object phase inversion": "+",
   "User Setup mapped object phase inversion": "+",
   "highlite": 0
  },
  {
   "Object": "/mcs4_core_i4004_id_board_n0362_reg/U$1",
   "Type": "DFF",
   "Mapping": "/mcs4_core_i4004_id_board_n0362_reg/U$1",
   "Phase": "+",
   "User Setup object phase inversion": "+",
   "User Setup mapped object phase inversion": "+",
   "highlite": 0
  },
  {
   "Object": "/mcs4_core_i4004_id_board_n0380_reg/U$1",
   "Type": "DFF",
   "Mapping": "/mcs4_core_i4004_id_board_n0380_reg/U$1",
   "Phase": "+",
   "User Setup object phase inversion": "+",
   "User Setup mapped object phase inversion": "+",
   "highlite": 0
  },
  {
   "Object": "/mcs4_core_i4004_id_board_n0397_reg/U$1",
   "Type": "DFF",
   "Mapping": "/mcs4_core_i4004_id_board_n0397_reg/U$1",
   "Phase": "+",
   "User Setup object phase inversion": "+",
   "User Setup mapped object phase inversion": "+",
   "highlite": 0
  },
  {
   "Object": "/mcs4_core_i4004_id_board_n0405_reg/U$1",
   "Type": "DFF",
   "Mapping": "/mcs4_core_i4004_id_board_n0405_reg/U$1",
   "Phase": "+",
   "User Setup object phase inversion": "+",
   "User Setup mapped object phase inversion": "+",
   "highlite": 0
  },
  {
   "Object": "/mcs4_core_i4004_id_board_n0414_reg/U$1",
   "Type": "DFF",
   "Mapping": "/mcs4_core_i4004_id_board_n0414_reg/U$1",
   "Phase": "+",
   "User Setup object phase inversion": "+",
   "User Setup mapped object phase inversion": "+",
   "highlite": 0
  },
  {
   "Object": "/mcs4_core_i4004_id_board_n0425_reg/U$1",
   "Type": "DFF",
   "Mapping": "/mcs4_core_i4004_id_board_n0425_reg/U$1",
   "Phase": "+",
   "User Setup object phase inversion": "+",
   "User Setup mapped object phase inversion": "+",
   "highlite": 0
  },
  {
   "Object": "/mcs4_core_i4004_id_board_n0433_reg/U$1",
   "Type": "DFF",
   "Mapping": "/mcs4_core_i4004_id_board_n0433_reg/U$1",
   "Phase": "+",
   "User Setup object phase inversion": "+",
   "User Setup mapped object phase inversion": "+",
   "highlite": 0
  },
  {
   "Object": "/mcs4_core_i4004_id_board_n0797_reg/U$1",
   "Type": "DFF",
   "Mapping": "/mcs4_core_i4004_id_board_n0797_reg/U$1",
   "Phase": "+",
   "User Setup object phase inversion": "+",
   "User Setup mapped object phase inversion": "+",
   "highlite": 0
  },
  {
   "Object": "/mcs4_core_i4004_id_board_n0801_reg/U$1",
   "Type": "DFF",
   "Mapping": "/mcs4_core_i4004_id_board_n0801_reg/U$1",
   "Phase": "+",
   "User Setup object phase inversion": "+",
   "User Setup mapped object phase inversion": "+",
   "highlite": 0
  },
  {
   "Object": "/mcs4_core_i4004_id_board_n0805_reg/U$1",
   "Type": "DFF",
   "Mapping": "/mcs4_core_i4004_id_board_n0805_reg/U$1",
   "Phase": "+",
   "User Setup object phase inversion": "+",
   "User Setup mapped object phase inversion": "+",
   "highlite": 0
  },
  {
   "Object": "/mcs4_core_i4004_id_board_opa_reg[1]/U$1",
   "Type": "DFF",
   "Mapping": "/mcs4_core_i4004_id_board_opa_reg[1]/U$1",
   "Phase": "+",
   "User Setup object phase inversion": "+",
   "User Setup mapped object phase inversion": "+",
   "highlite": 0
  },
  {
   "Object": "/mcs4_core_i4004_id_board_opa_reg[2]/U$1",
   "Type": "DFF",
   "Mapping": "/mcs4_core_i4004_id_board_opa_reg[2]/U$1",
   "Phase": "+",
   "User Setup object phase inversion": "+",
   "User Setup mapped object phase inversion": "+",
   "highlite": 0
  },
  {
   "Object": "/mcs4_core_i4004_id_board_opa_reg[3]/U$1",
   "Type": "DFF",
   "Mapping": "/mcs4_core_i4004_id_board_opa_reg[3]/U$1",
   "Phase": "+",
   "User Setup object phase inversion": "+",
   "User Setup mapped object phase inversion": "+",
   "highlite": 0
  },
  {
   "Object": "/mcs4_core_i4004_id_board_opr_reg[0]/U$1",
   "Type": "DFF",
   "Mapping": "/mcs4_core_i4004_id_board_opr_reg[0]/U$1",
   "Phase": "+",
   "User Setup object phase inversion": "+",
   "User Setup mapped object phase inversion": "+",
   "highlite": 0
  },
  {
   "Object": "/mcs4_core_i4004_id_board_opr_reg[1]/U$1",
   "Type": "DFF",
   "Mapping": "/mcs4_core_i4004_id_board_opr_reg[1]/U$1",
   "Phase": "+",
   "User Setup object phase inversion": "+",
   "User Setup mapped object phase inversion": "+",
   "highlite": 0
  },
  {
   "Object": "/mcs4_core_i4004_id_board_opr_reg[2]/U$1",
   "Type": "DFF",
   "Mapping": "/mcs4_core_i4004_id_board_opr_reg[2]/U$1",
   "Phase": "+",
   "User Setup object phase inversion": "+",
   "User Setup mapped object phase inversion": "+",
   "highlite": 0
  },
  {
   "Object": "/mcs4_core_i4004_id_board_opr_reg[3]/U$1",
   "Type": "DFF",
   "Mapping": "/mcs4_core_i4004_id_board_opr_reg[3]/U$1",
   "Phase": "+",
   "User Setup object phase inversion": "+",
   "User Setup mapped object phase inversion": "+",
   "highlite": 0
  },
  {
   "Object": "/mcs4_core_i4004_ip_board_addr_ptr_0_master_reg/U$1",
   "Type": "DFF",
   "Mapping": "/mcs4_core_i4004_ip_board_addr_ptr_0_master_reg/U$1",
   "Phase": "+",
   "User Setup object phase inversion": "+",
   "User Setup mapped object phase inversion": "+",
   "highlite": 0
  },
  {
   "Object": "/mcs4_core_i4004_ip_board_addr_ptr_0_slave_reg/U$1",
   "Type": "DFF",
   "Mapping": "/mcs4_core_i4004_ip_board_addr_ptr_0_slave_reg/U$1",
   "Phase": "+",
   "User Setup object phase inversion": "+",
   "User Setup mapped object phase inversion": "+",
   "highlite": 0
  },
  {
   "Object": "/mcs4_core_i4004_ip_board_addr_ptr_1_master_reg/U$1",
   "Type": "DFF",
   "Mapping": "/mcs4_core_i4004_ip_board_addr_ptr_1_master_reg/U$1",
   "Phase": "+",
   "User Setup object phase inversion": "+",
   "User Setup mapped object phase inversion": "+",
   "highlite": 0
  },
  {
   "Object": "/mcs4_core_i4004_ip_board_addr_ptr_1_slave_reg/U$1",
   "Type": "DFF",
   "Mapping": "/mcs4_core_i4004_ip_board_addr_ptr_1_slave_reg/U$1",
   "Phase": "+",
   "User Setup object phase inversion": "+",
   "User Setup mapped object phase inversion": "+",
   "highlite": 0
  },
  {
   "Object": "/mcs4_core_i4004_ip_board_addr_rfsh_0_master_reg/U$1",
   "Type": "DFF",
   "Mapping": "/mcs4_core_i4004_ip_board_addr_rfsh_0_master_reg/U$1",
   "Phase": "+",
   "User Setup object phase inversion": "+",
   "User Setup mapped object phase inversion": "+",
   "highlite": 0
  },
  {
   "Object": "/mcs4_core_i4004_ip_board_addr_rfsh_0_slave_reg/U$1",
   "Type": "DFF",
   "Mapping": "/mcs4_core_i4004_ip_board_addr_rfsh_0_slave_reg/U$1",
   "Phase": "+",
   "User Setup object phase inversion": "+",
   "User Setup mapped object phase inversion": "+",
   "highlite": 0
  },
  {
   "Object": "/mcs4_core_i4004_ip_board_addr_rfsh_1_master_reg/U$1",
   "Type": "DFF",
   "Mapping": "/mcs4_core_i4004_ip_board_addr_rfsh_1_master_reg/U$1",
   "Phase": "+",
   "User Setup object phase inversion": "+",
   "User Setup mapped object phase inversion": "+",
   "highlite": 0
  },
  {
   "Object": "/mcs4_core_i4004_ip_board_addr_rfsh_1_slave_reg/U$1",
   "Type": "DFF",
   "Mapping": "/mcs4_core_i4004_ip_board_addr_rfsh_1_slave_reg/U$1",
   "Phase": "+",
   "User Setup object phase inversion": "+",
   "User Setup mapped object phase inversion": "+",
   "highlite": 0
  },
  {
   "Object": "/mcs4_core_i4004_ip_board_carry_in_reg/U$1",
   "Type": "DFF",
   "Mapping": "/mcs4_core_i4004_ip_board_carry_in_reg/U$1",
   "Phase": "+",
   "User Setup object phase inversion": "+",
   "User Setup mapped object phase inversion": "+",
   "highlite": 0
  },
  {
   "Object": "/mcs4_core_i4004_ip_board_carry_out_reg/U$1",
   "Type": "DFF",
   "Mapping": "/mcs4_core_i4004_ip_board_carry_out_reg/U$1",
   "Phase": "+",
   "User Setup object phase inversion": "+",
   "User Setup mapped object phase inversion": "+",
   "highlite": 0
  },
  {
   "Object": "/mcs4_core_i4004_ip_board_dram_array_reg[0][0]/U$1",
   "Type": "DFF",
   "Mapping": "/mcs4_core_i4004_ip_board_dram_array_reg[0][0]/U$1",
   "Phase": "+",
   "User Setup object phase inversion": "+",
   "User Setup mapped object phase inversion": "+",
   "highlite": 0
  },
  {
   "Object": "/mcs4_core_i4004_ip_board_dram_array_reg[0][1]/U$1",
   "Type": "DFF",
   "Mapping": "/mcs4_core_i4004_ip_board_dram_array_reg[0][1]/U$1",
   "Phase": "+",
   "User Setup object phase inversion": "+",
   "User Setup mapped object phase inversion": "+",
   "highlite": 0
  },
  {
   "Object": "/mcs4_core_i4004_ip_board_dram_array_reg[0][2]/U$1",
   "Type": "DFF",
   "Mapping": "/mcs4_core_i4004_ip_board_dram_array_reg[0][2]/U$1",
   "Phase": "+",
   "User Setup object phase inversion": "+",
   "User Setup mapped object phase inversion": "+",
   "highlite": 0
  },
  {
   "Object": "/mcs4_core_i4004_ip_board_dram_array_reg[0][3]/U$1",
   "Type": "DFF",
   "Mapping": "/mcs4_core_i4004_ip_board_dram_array_reg[0][3]/U$1",
   "Phase": "+",
   "User Setup object phase inversion": "+",
   "User Setup mapped object phase inversion": "+",
   "highlite": 0
  },
  {
   "Object": "/mcs4_core_i4004_ip_board_dram_array_reg[0][4]/U$1",
   "Type": "DFF",
   "Mapping": "/mcs4_core_i4004_ip_board_dram_array_reg[0][4]/U$1",
   "Phase": "+",
   "User Setup object phase inversion": "+",
   "User Setup mapped object phase inversion": "+",
   "highlite": 0
  },
  {
   "Object": "/mcs4_core_i4004_ip_board_dram_array_reg[0][5]/U$1",
   "Type": "DFF",
   "Mapping": "/mcs4_core_i4004_ip_board_dram_array_reg[0][5]/U$1",
   "Phase": "+",
   "User Setup object phase inversion": "+",
   "User Setup mapped object phase inversion": "+",
   "highlite": 0
  },
  {
   "Object": "/mcs4_core_i4004_ip_board_dram_array_reg[0][6]/U$1",
   "Type": "DFF",
   "Mapping": "/mcs4_core_i4004_ip_board_dram_array_reg[0][6]/U$1",
   "Phase": "+",
   "User Setup object phase inversion": "+",
   "User Setup mapped object phase inversion": "+",
   "highlite": 0
  },
  {
   "Object": "/mcs4_core_i4004_ip_board_dram_array_reg[0][7]/U$1",
   "Type": "DFF",
   "Mapping": "/mcs4_core_i4004_ip_board_dram_array_reg[0][7]/U$1",
   "Phase": "+",
   "User Setup object phase inversion": "+",
   "User Setup mapped object phase inversion": "+",
   "highlite": 0
  },
  {
   "Object": "/mcs4_core_i4004_ip_board_dram_array_reg[0][8]/U$1",
   "Type": "DFF",
   "Mapping": "/mcs4_core_i4004_ip_board_dram_array_reg[0][8]/U$1",
   "Phase": "+",
   "User Setup object phase inversion": "+",
   "User Setup mapped object phase inversion": "+",
   "highlite": 0
  },
  {
   "Object": "/mcs4_core_i4004_ip_board_dram_array_reg[0][9]/U$1",
   "Type": "DFF",
   "Mapping": "/mcs4_core_i4004_ip_board_dram_array_reg[0][9]/U$1",
   "Phase": "+",
   "User Setup object phase inversion": "+",
   "User Setup mapped object phase inversion": "+",
   "highlite": 0
  },
  {
   "Object": "/mcs4_core_i4004_ip_board_dram_array_reg[0][10]/U$1",
   "Type": "DFF",
   "Mapping": "/mcs4_core_i4004_ip_board_dram_array_reg[0][10]/U$1",
   "Phase": "+",
   "User Setup object phase inversion": "+",
   "User Setup mapped object phase inversion": "+",
   "highlite": 0
  },
  {
   "Object": "/mcs4_core_i4004_ip_board_dram_array_reg[0][11]/U$1",
   "Type": "DFF",
   "Mapping": "/mcs4_core_i4004_ip_board_dram_array_reg[0][11]/U$1",
   "Phase": "+",
   "User Setup object phase inversion": "+",
   "User Setup mapped object phase inversion": "+",
   "highlite": 0
  },
  {
   "Object": "/mcs4_core_i4004_ip_board_dram_array_reg[1][0]/U$1",
   "Type": "DFF",
   "Mapping": "/mcs4_core_i4004_ip_board_dram_array_reg[1][0]/U$1",
   "Phase": "+",
   "User Setup object phase inversion": "+",
   "User Setup mapped object phase inversion": "+",
   "highlite": 0
  },
  {
   "Object": "/mcs4_core_i4004_ip_board_dram_array_reg[1][1]/U$1",
   "Type": "DFF",
   "Mapping": "/mcs4_core_i4004_ip_board_dram_array_reg[1][1]/U$1",
   "Phase": "+",
   "User Setup object phase inversion": "+",
   "User Setup mapped object phase inversion": "+",
   "highlite": 0
  },
  {
   "Object": "/mcs4_core_i4004_ip_board_dram_array_reg[1][2]/U$1",
   "Type": "DFF",
   "Mapping": "/mcs4_core_i4004_ip_board_dram_array_reg[1][2]/U$1",
   "Phase": "+",
   "User Setup object phase inversion": "+",
   "User Setup mapped object phase inversion": "+",
   "highlite": 0
  },
  {
   "Object": "/mcs4_core_i4004_ip_board_dram_array_reg[1][3]/U$1",
   "Type": "DFF",
   "Mapping": "/mcs4_core_i4004_ip_board_dram_array_reg[1][3]/U$1",
   "Phase": "+",
   "User Setup object phase inversion": "+",
   "User Setup mapped object phase inversion": "+",
   "highlite": 0
  },
  {
   "Object": "/mcs4_core_i4004_ip_board_dram_array_reg[1][4]/U$1",
   "Type": "DFF",
   "Mapping": "/mcs4_core_i4004_ip_board_dram_array_reg[1][4]/U$1",
   "Phase": "+",
   "User Setup object phase inversion": "+",
   "User Setup mapped object phase inversion": "+",
   "highlite": 0
  },
  {
   "Object": "/mcs4_core_i4004_ip_board_dram_array_reg[1][5]/U$1",
   "Type": "DFF",
   "Mapping": "/mcs4_core_i4004_ip_board_dram_array_reg[1][5]/U$1",
   "Phase": "+",
   "User Setup object phase inversion": "+",
   "User Setup mapped object phase inversion": "+",
   "highlite": 0
  },
  {
   "Object": "/mcs4_core_i4004_ip_board_dram_array_reg[1][6]/U$1",
   "Type": "DFF",
   "Mapping": "/mcs4_core_i4004_ip_board_dram_array_reg[1][6]/U$1",
   "Phase": "+",
   "User Setup object phase inversion": "+",
   "User Setup mapped object phase inversion": "+",
   "highlite": 0
  },
  {
   "Object": "/mcs4_core_i4004_ip_board_dram_array_reg[1][7]/U$1",
   "Type": "DFF",
   "Mapping": "/mcs4_core_i4004_ip_board_dram_array_reg[1][7]/U$1",
   "Phase": "+",
   "User Setup object phase inversion": "+",
   "User Setup mapped object phase inversion": "+",
   "highlite": 0
  },
  {
   "Object": "/mcs4_core_i4004_ip_board_dram_array_reg[1][8]/U$1",
   "Type": "DFF",
   "Mapping": "/mcs4_core_i4004_ip_board_dram_array_reg[1][8]/U$1",
   "Phase": "+",
   "User Setup object phase inversion": "+",
   "User Setup mapped object phase inversion": "+",
   "highlite": 0
  },
  {
   "Object": "/mcs4_core_i4004_ip_board_dram_array_reg[1][9]/U$1",
   "Type": "DFF",
   "Mapping": "/mcs4_core_i4004_ip_board_dram_array_reg[1][9]/U$1",
   "Phase": "+",
   "User Setup object phase inversion": "+",
   "User Setup mapped object phase inversion": "+",
   "highlite": 0
  },
  {
   "Object": "/mcs4_core_i4004_ip_board_dram_array_reg[1][10]/U$1",
   "Type": "DFF",
   "Mapping": "/mcs4_core_i4004_ip_board_dram_array_reg[1][10]/U$1",
   "Phase": "+",
   "User Setup object phase inversion": "+",
   "User Setup mapped object phase inversion": "+",
   "highlite": 0
  },
  {
   "Object": "/mcs4_core_i4004_ip_board_dram_array_reg[1][11]/U$1",
   "Type": "DFF",
   "Mapping": "/mcs4_core_i4004_ip_board_dram_array_reg[1][11]/U$1",
   "Phase": "+",
   "User Setup object phase inversion": "+",
   "User Setup mapped object phase inversion": "+",
   "highlite": 0
  },
  {
   "Object": "/mcs4_core_i4004_ip_board_dram_array_reg[2][0]/U$1",
   "Type": "DFF",
   "Mapping": "/mcs4_core_i4004_ip_board_dram_array_reg[2][0]/U$1",
   "Phase": "+",
   "User Setup object phase inversion": "+",
   "User Setup mapped object phase inversion": "+",
   "highlite": 0
  },
  {
   "Object": "/mcs4_core_i4004_ip_board_dram_array_reg[2][1]/U$1",
   "Type": "DFF",
   "Mapping": "/mcs4_core_i4004_ip_board_dram_array_reg[2][1]/U$1",
   "Phase": "+",
   "User Setup object phase inversion": "+",
   "User Setup mapped object phase inversion": "+",
   "highlite": 0
  },
  {
   "Object": "/mcs4_core_i4004_ip_board_dram_array_reg[2][2]/U$1",
   "Type": "DFF",
   "Mapping": "/mcs4_core_i4004_ip_board_dram_array_reg[2][2]/U$1",
   "Phase": "+",
   "User Setup object phase inversion": "+",
   "User Setup mapped object phase inversion": "+",
   "highlite": 0
  },
  {
   "Object": "/mcs4_core_i4004_ip_board_dram_array_reg[2][3]/U$1",
   "Type": "DFF",
   "Mapping": "/mcs4_core_i4004_ip_board_dram_array_reg[2][3]/U$1",
   "Phase": "+",
   "User Setup object phase inversion": "+",
   "User Setup mapped object phase inversion": "+",
   "highlite": 0
  },
  {
   "Object": "/mcs4_core_i4004_ip_board_dram_array_reg[2][4]/U$1",
   "Type": "DFF",
   "Mapping": "/mcs4_core_i4004_ip_board_dram_array_reg[2][4]/U$1",
   "Phase": "+",
   "User Setup object phase inversion": "+",
   "User Setup mapped object phase inversion": "+",
   "highlite": 0
  },
  {
   "Object": "/mcs4_core_i4004_ip_board_dram_array_reg[2][5]/U$1",
   "Type": "DFF",
   "Mapping": "/mcs4_core_i4004_ip_board_dram_array_reg[2][5]/U$1",
   "Phase": "+",
   "User Setup object phase inversion": "+",
   "User Setup mapped object phase inversion": "+",
   "highlite": 0
  },
  {
   "Object": "/mcs4_core_i4004_ip_board_dram_array_reg[2][6]/U$1",
   "Type": "DFF",
   "Mapping": "/mcs4_core_i4004_ip_board_dram_array_reg[2][6]/U$1",
   "Phase": "+",
   "User Setup object phase inversion": "+",
   "User Setup mapped object phase inversion": "+",
   "highlite": 0
  },
  {
   "Object": "/mcs4_core_i4004_ip_board_dram_array_reg[2][7]/U$1",
   "Type": "DFF",
   "Mapping": "/mcs4_core_i4004_ip_board_dram_array_reg[2][7]/U$1",
   "Phase": "+",
   "User Setup object phase inversion": "+",
   "User Setup mapped object phase inversion": "+",
   "highlite": 0
  },
  {
   "Object": "/mcs4_core_i4004_ip_board_dram_array_reg[2][8]/U$1",
   "Type": "DFF",
   "Mapping": "/mcs4_core_i4004_ip_board_dram_array_reg[2][8]/U$1",
   "Phase": "+",
   "User Setup object phase inversion": "+",
   "User Setup mapped object phase inversion": "+",
   "highlite": 0
  },
  {
   "Object": "/mcs4_core_i4004_ip_board_dram_array_reg[2][9]/U$1",
   "Type": "DFF",
   "Mapping": "/mcs4_core_i4004_ip_board_dram_array_reg[2][9]/U$1",
   "Phase": "+",
   "User Setup object phase inversion": "+",
   "User Setup mapped object phase inversion": "+",
   "highlite": 0
  },
  {
   "Object": "/mcs4_core_i4004_ip_board_dram_array_reg[2][10]/U$1",
   "Type": "DFF",
   "Mapping": "/mcs4_core_i4004_ip_board_dram_array_reg[2][10]/U$1",
   "Phase": "+",
   "User Setup object phase inversion": "+",
   "User Setup mapped object phase inversion": "+",
   "highlite": 0
  },
  {
   "Object": "/mcs4_core_i4004_ip_board_dram_array_reg[2][11]/U$1",
   "Type": "DFF",
   "Mapping": "/mcs4_core_i4004_ip_board_dram_array_reg[2][11]/U$1",
   "Phase": "+",
   "User Setup object phase inversion": "+",
   "User Setup mapped object phase inversion": "+",
   "highlite": 0
  },
  {
   "Object": "/mcs4_core_i4004_ip_board_dram_array_reg[3][0]/U$1",
   "Type": "DFF",
   "Mapping": "/mcs4_core_i4004_ip_board_dram_array_reg[3][0]/U$1",
   "Phase": "+",
   "User Setup object phase inversion": "+",
   "User Setup mapped object phase inversion": "+",
   "highlite": 0
  },
  {
   "Object": "/mcs4_core_i4004_ip_board_dram_array_reg[3][1]/U$1",
   "Type": "DFF",
   "Mapping": "/mcs4_core_i4004_ip_board_dram_array_reg[3][1]/U$1",
   "Phase": "+",
   "User Setup object phase inversion": "+",
   "User Setup mapped object phase inversion": "+",
   "highlite": 0
  },
  {
   "Object": "/mcs4_core_i4004_ip_board_dram_array_reg[3][2]/U$1",
   "Type": "DFF",
   "Mapping": "/mcs4_core_i4004_ip_board_dram_array_reg[3][2]/U$1",
   "Phase": "+",
   "User Setup object phase inversion": "+",
   "User Setup mapped object phase inversion": "+",
   "highlite": 0
  },
  {
   "Object": "/mcs4_core_i4004_ip_board_dram_array_reg[3][3]/U$1",
   "Type": "DFF",
   "Mapping": "/mcs4_core_i4004_ip_board_dram_array_reg[3][3]/U$1",
   "Phase": "+",
   "User Setup object phase inversion": "+",
   "User Setup mapped object phase inversion": "+",
   "highlite": 0
  },
  {
   "Object": "/mcs4_core_i4004_ip_board_dram_array_reg[3][4]/U$1",
   "Type": "DFF",
   "Mapping": "/mcs4_core_i4004_ip_board_dram_array_reg[3][4]/U$1",
   "Phase": "+",
   "User Setup object phase inversion": "+",
   "User Setup mapped object phase inversion": "+",
   "highlite": 0
  },
  {
   "Object": "/mcs4_core_i4004_ip_board_dram_array_reg[3][5]/U$1",
   "Type": "DFF",
   "Mapping": "/mcs4_core_i4004_ip_board_dram_array_reg[3][5]/U$1",
   "Phase": "+",
   "User Setup object phase inversion": "+",
   "User Setup mapped object phase inversion": "+",
   "highlite": 0
  },
  {
   "Object": "/mcs4_core_i4004_ip_board_dram_array_reg[3][6]/U$1",
   "Type": "DFF",
   "Mapping": "/mcs4_core_i4004_ip_board_dram_array_reg[3][6]/U$1",
   "Phase": "+",
   "User Setup object phase inversion": "+",
   "User Setup mapped object phase inversion": "+",
   "highlite": 0
  },
  {
   "Object": "/mcs4_core_i4004_ip_board_dram_array_reg[3][7]/U$1",
   "Type": "DFF",
   "Mapping": "/mcs4_core_i4004_ip_board_dram_array_reg[3][7]/U$1",
   "Phase": "+",
   "User Setup object phase inversion": "+",
   "User Setup mapped object phase inversion": "+",
   "highlite": 0
  },
  {
   "Object": "/mcs4_core_i4004_ip_board_dram_array_reg[3][8]/U$1",
   "Type": "DFF",
   "Mapping": "/mcs4_core_i4004_ip_board_dram_array_reg[3][8]/U$1",
   "Phase": "+",
   "User Setup object phase inversion": "+",
   "User Setup mapped object phase inversion": "+",
   "highlite": 0
  },
  {
   "Object": "/mcs4_core_i4004_ip_board_dram_array_reg[3][9]/U$1",
   "Type": "DFF",
   "Mapping": "/mcs4_core_i4004_ip_board_dram_array_reg[3][9]/U$1",
   "Phase": "+",
   "User Setup object phase inversion": "+",
   "User Setup mapped object phase inversion": "+",
   "highlite": 0
  },
  {
   "Object": "/mcs4_core_i4004_ip_board_dram_array_reg[3][10]/U$1",
   "Type": "DFF",
   "Mapping": "/mcs4_core_i4004_ip_board_dram_array_reg[3][10]/U$1",
   "Phase": "+",
   "User Setup object phase inversion": "+",
   "User Setup mapped object phase inversion": "+",
   "highlite": 0
  },
  {
   "Object": "/mcs4_core_i4004_ip_board_dram_array_reg[3][11]/U$1",
   "Type": "DFF",
   "Mapping": "/mcs4_core_i4004_ip_board_dram_array_reg[3][11]/U$1",
   "Phase": "+",
   "User Setup object phase inversion": "+",
   "User Setup mapped object phase inversion": "+",
   "highlite": 0
  },
  {
   "Object": "/mcs4_core_i4004_ip_board_dram_temp_reg[0]/U$1",
   "Type": "DFF",
   "Mapping": "/mcs4_core_i4004_ip_board_dram_temp_reg[0]/U$1",
   "Phase": "+",
   "User Setup object phase inversion": "+",
   "User Setup mapped object phase inversion": "+",
   "highlite": 0
  },
  {
   "Object": "/mcs4_core_i4004_ip_board_dram_temp_reg[1]/U$1",
   "Type": "DFF",
   "Mapping": "/mcs4_core_i4004_ip_board_dram_temp_reg[1]/U$1",
   "Phase": "+",
   "User Setup object phase inversion": "+",
   "User Setup mapped object phase inversion": "+",
   "highlite": 0
  },
  {
   "Object": "/mcs4_core_i4004_ip_board_dram_temp_reg[2]/U$1",
   "Type": "DFF",
   "Mapping": "/mcs4_core_i4004_ip_board_dram_temp_reg[2]/U$1",
   "Phase": "+",
   "User Setup object phase inversion": "+",
   "User Setup mapped object phase inversion": "+",
   "highlite": 0
  },
  {
   "Object": "/mcs4_core_i4004_ip_board_dram_temp_reg[3]/U$1",
   "Type": "DFF",
   "Mapping": "/mcs4_core_i4004_ip_board_dram_temp_reg[3]/U$1",
   "Phase": "+",
   "User Setup object phase inversion": "+",
   "User Setup mapped object phase inversion": "+",
   "highlite": 0
  },
  {
   "Object": "/mcs4_core_i4004_ip_board_dram_temp_reg[4]/U$1",
   "Type": "DFF",
   "Mapping": "/mcs4_core_i4004_ip_board_dram_temp_reg[4]/U$1",
   "Phase": "+",
   "User Setup object phase inversion": "+",
   "User Setup mapped object phase inversion": "+",
   "highlite": 0
  },
  {
   "Object": "/mcs4_core_i4004_ip_board_dram_temp_reg[5]/U$1",
   "Type": "DFF",
   "Mapping": "/mcs4_core_i4004_ip_board_dram_temp_reg[5]/U$1",
   "Phase": "+",
   "User Setup object phase inversion": "+",
   "User Setup mapped object phase inversion": "+",
   "highlite": 0
  },
  {
   "Object": "/mcs4_core_i4004_ip_board_dram_temp_reg[6]/U$1",
   "Type": "DFF",
   "Mapping": "/mcs4_core_i4004_ip_board_dram_temp_reg[6]/U$1",
   "Phase": "+",
   "User Setup object phase inversion": "+",
   "User Setup mapped object phase inversion": "+",
   "highlite": 0
  },
  {
   "Object": "/mcs4_core_i4004_ip_board_dram_temp_reg[7]/U$1",
   "Type": "DFF",
   "Mapping": "/mcs4_core_i4004_ip_board_dram_temp_reg[7]/U$1",
   "Phase": "+",
   "User Setup object phase inversion": "+",
   "User Setup mapped object phase inversion": "+",
   "highlite": 0
  },
  {
   "Object": "/mcs4_core_i4004_ip_board_dram_temp_reg[8]/U$1",
   "Type": "DFF",
   "Mapping": "/mcs4_core_i4004_ip_board_dram_temp_reg[8]/U$1",
   "Phase": "+",
   "User Setup object phase inversion": "+",
   "User Setup mapped object phase inversion": "+",
   "highlite": 0
  },
  {
   "Object": "/mcs4_core_i4004_ip_board_dram_temp_reg[9]/U$1",
   "Type": "DFF",
   "Mapping": "/mcs4_core_i4004_ip_board_dram_temp_reg[9]/U$1",
   "Phase": "+",
   "User Setup object phase inversion": "+",
   "User Setup mapped object phase inversion": "+",
   "highlite": 0
  },
  {
   "Object": "/mcs4_core_i4004_ip_board_dram_temp_reg[10]/U$1",
   "Type": "DFF",
   "Mapping": "/mcs4_core_i4004_ip_board_dram_temp_reg[10]/U$1",
   "Phase": "+",
   "User Setup object phase inversion": "+",
   "User Setup mapped object phase inversion": "+",
   "highlite": 0
  },
  {
   "Object": "/mcs4_core_i4004_ip_board_dram_temp_reg[11]/U$1",
   "Type": "DFF",
   "Mapping": "/mcs4_core_i4004_ip_board_dram_temp_reg[11]/U$1",
   "Phase": "+",
   "User Setup object phase inversion": "+",
   "User Setup mapped object phase inversion": "+",
   "highlite": 0
  },
  {
   "Object": "/mcs4_core_i4004_ip_board_incr_in_reg[0]/U$1",
   "Type": "DFF",
   "Mapping": "/mcs4_core_i4004_ip_board_incr_in_reg[0]/U$1",
   "Phase": "+",
   "User Setup object phase inversion": "+",
   "User Setup mapped object phase inversion": "+",
   "highlite": 0
  },
  {
   "Object": "/mcs4_core_i4004_ip_board_incr_in_reg[1]/U$1",
   "Type": "DFF",
   "Mapping": "/mcs4_core_i4004_ip_board_incr_in_reg[1]/U$1",
   "Phase": "+",
   "User Setup object phase inversion": "+",
   "User Setup mapped object phase inversion": "+",
   "highlite": 0
  },
  {
   "Object": "/mcs4_core_i4004_ip_board_incr_in_reg[2]/U$1",
   "Type": "DFF",
   "Mapping": "/mcs4_core_i4004_ip_board_incr_in_reg[2]/U$1",
   "Phase": "+",
   "User Setup object phase inversion": "+",
   "User Setup mapped object phase inversion": "+",
   "highlite": 0
  },
  {
   "Object": "/mcs4_core_i4004_ip_board_incr_in_reg[3]/U$1",
   "Type": "DFF",
   "Mapping": "/mcs4_core_i4004_ip_board_incr_in_reg[3]/U$1",
   "Phase": "+",
   "User Setup object phase inversion": "+",
   "User Setup mapped object phase inversion": "+",
   "highlite": 0
  },
  {
   "Object": "/mcs4_core_i4004_ip_board_n0374_reg/U$1",
   "Type": "DFF",
   "Mapping": "/mcs4_core_i4004_ip_board_n0374_reg/U$1",
   "Phase": "+",
   "User Setup object phase inversion": "+",
   "User Setup mapped object phase inversion": "+",
   "highlite": 0
  },
  {
   "Object": "/mcs4_core_i4004_ip_board_n0384_reg/U$1",
   "Type": "DFF",
   "Mapping": "/mcs4_core_i4004_ip_board_n0384_reg/U$1",
   "Phase": "+",
   "User Setup object phase inversion": "+",
   "User Setup mapped object phase inversion": "+",
   "highlite": 0
  },
  {
   "Object": "/mcs4_core_i4004_ip_board_n0416_reg/U$1",
   "Type": "DFF",
   "Mapping": "/mcs4_core_i4004_ip_board_n0416_reg/U$1",
   "Phase": "+",
   "User Setup object phase inversion": "+",
   "User Setup mapped object phase inversion": "+",
   "highlite": 0
  },
  {
   "Object": "/mcs4_core_i4004_ip_board_n0438_reg/U$1",
   "Type": "DFF",
   "Mapping": "/mcs4_core_i4004_ip_board_n0438_reg/U$1",
   "Phase": "+",
   "User Setup object phase inversion": "+",
   "User Setup mapped object phase inversion": "+",
   "highlite": 0
  },
  {
   "Object": "/mcs4_core_i4004_ip_board_n0517_reg/U$1",
   "Type": "DFF",
   "Mapping": "/mcs4_core_i4004_ip_board_n0517_reg/U$1",
   "Phase": "+",
   "User Setup object phase inversion": "+",
   "User Setup mapped object phase inversion": "+",
   "highlite": 0
  },
  {
   "Object": "/mcs4_core_i4004_sp_board_din_n_reg[0]/U$1",
   "Type": "DFF",
   "Mapping": "/mcs4_core_i4004_sp_board_din_n_reg[0]/U$1",
   "Phase": "+",
   "User Setup object phase inversion": "+",
   "User Setup mapped object phase inversion": "+",
   "highlite": 0
  },
  {
   "Object": "/mcs4_core_i4004_sp_board_din_n_reg[1]/U$1",
   "Type": "DFF",
   "Mapping": "/mcs4_core_i4004_sp_board_din_n_reg[1]/U$1",
   "Phase": "+",
   "User Setup object phase inversion": "+",
   "User Setup mapped object phase inversion": "+",
   "highlite": 0
  },
  {
   "Object": "/mcs4_core_i4004_sp_board_din_n_reg[2]/U$1",
   "Type": "DFF",
   "Mapping": "/mcs4_core_i4004_sp_board_din_n_reg[2]/U$1",
   "Phase": "+",
   "User Setup object phase inversion": "+",
   "User Setup mapped object phase inversion": "+",
   "highlite": 0
  },
  {
   "Object": "/mcs4_core_i4004_sp_board_din_n_reg[3]/U$1",
   "Type": "DFF",
   "Mapping": "/mcs4_core_i4004_sp_board_din_n_reg[3]/U$1",
   "Phase": "+",
   "User Setup object phase inversion": "+",
   "User Setup mapped object phase inversion": "+",
   "highlite": 0
  },
  {
   "Object": "/mcs4_core_i4004_sp_board_dram_array_reg[0][0]/U$1",
   "Type": "DFF",
   "Mapping": "/mcs4_core_i4004_sp_board_dram_array_reg[0][0]/U$1",
   "Phase": "+",
   "User Setup object phase inversion": "+",
   "User Setup mapped object phase inversion": "+",
   "highlite": 0
  },
  {
   "Object": "/mcs4_core_i4004_sp_board_dram_array_reg[0][1]/U$1",
   "Type": "DFF",
   "Mapping": "/mcs4_core_i4004_sp_board_dram_array_reg[0][1]/U$1",
   "Phase": "+",
   "User Setup object phase inversion": "+",
   "User Setup mapped object phase inversion": "+",
   "highlite": 0
  },
  {
   "Object": "/mcs4_core_i4004_sp_board_dram_array_reg[0][2]/U$1",
   "Type": "DFF",
   "Mapping": "/mcs4_core_i4004_sp_board_dram_array_reg[0][2]/U$1",
   "Phase": "+",
   "User Setup object phase inversion": "+",
   "User Setup mapped object phase inversion": "+",
   "highlite": 0
  },
  {
   "Object": "/mcs4_core_i4004_sp_board_dram_array_reg[0][3]/U$1",
   "Type": "DFF",
   "Mapping": "/mcs4_core_i4004_sp_board_dram_array_reg[0][3]/U$1",
   "Phase": "+",
   "User Setup object phase inversion": "+",
   "User Setup mapped object phase inversion": "+",
   "highlite": 0
  },
  {
   "Object": "/mcs4_core_i4004_sp_board_dram_array_reg[0][4]/U$1",
   "Type": "DFF",
   "Mapping": "/mcs4_core_i4004_sp_board_dram_array_reg[0][4]/U$1",
   "Phase": "+",
   "User Setup object phase inversion": "+",
   "User Setup mapped object phase inversion": "+",
   "highlite": 0
  },
  {
   "Object": "/mcs4_core_i4004_sp_board_dram_array_reg[0][5]/U$1",
   "Type": "DFF",
   "Mapping": "/mcs4_core_i4004_sp_board_dram_array_reg[0][5]/U$1",
   "Phase": "+",
   "User Setup object phase inversion": "+",
   "User Setup mapped object phase inversion": "+",
   "highlite": 0
  },
  {
   "Object": "/mcs4_core_i4004_sp_board_dram_array_reg[0][6]/U$1",
   "Type": "DFF",
   "Mapping": "/mcs4_core_i4004_sp_board_dram_array_reg[0][6]/U$1",
   "Phase": "+",
   "User Setup object phase inversion": "+",
   "User Setup mapped object phase inversion": "+",
   "highlite": 0
  },
  {
   "Object": "/mcs4_core_i4004_sp_board_dram_array_reg[0][7]/U$1",
   "Type": "DFF",
   "Mapping": "/mcs4_core_i4004_sp_board_dram_array_reg[0][7]/U$1",
   "Phase": "+",
   "User Setup object phase inversion": "+",
   "User Setup mapped object phase inversion": "+",
   "highlite": 0
  },
  {
   "Object": "/mcs4_core_i4004_sp_board_dram_array_reg[1][0]/U$1",
   "Type": "DFF",
   "Mapping": "/mcs4_core_i4004_sp_board_dram_array_reg[1][0]/U$1",
   "Phase": "+",
   "User Setup object phase inversion": "+",
   "User Setup mapped object phase inversion": "+",
   "highlite": 0
  },
  {
   "Object": "/mcs4_core_i4004_sp_board_dram_array_reg[1][1]/U$1",
   "Type": "DFF",
   "Mapping": "/mcs4_core_i4004_sp_board_dram_array_reg[1][1]/U$1",
   "Phase": "+",
   "User Setup object phase inversion": "+",
   "User Setup mapped object phase inversion": "+",
   "highlite": 0
  },
  {
   "Object": "/mcs4_core_i4004_sp_board_dram_array_reg[1][2]/U$1",
   "Type": "DFF",
   "Mapping": "/mcs4_core_i4004_sp_board_dram_array_reg[1][2]/U$1",
   "Phase": "+",
   "User Setup object phase inversion": "+",
   "User Setup mapped object phase inversion": "+",
   "highlite": 0
  },
  {
   "Object": "/mcs4_core_i4004_sp_board_dram_array_reg[1][3]/U$1",
   "Type": "DFF",
   "Mapping": "/mcs4_core_i4004_sp_board_dram_array_reg[1][3]/U$1",
   "Phase": "+",
   "User Setup object phase inversion": "+",
   "User Setup mapped object phase inversion": "+",
   "highlite": 0
  },
  {
   "Object": "/mcs4_core_i4004_sp_board_dram_array_reg[1][4]/U$1",
   "Type": "DFF",
   "Mapping": "/mcs4_core_i4004_sp_board_dram_array_reg[1][4]/U$1",
   "Phase": "+",
   "User Setup object phase inversion": "+",
   "User Setup mapped object phase inversion": "+",
   "highlite": 0
  },
  {
   "Object": "/mcs4_core_i4004_sp_board_dram_array_reg[1][5]/U$1",
   "Type": "DFF",
   "Mapping": "/mcs4_core_i4004_sp_board_dram_array_reg[1][5]/U$1",
   "Phase": "+",
   "User Setup object phase inversion": "+",
   "User Setup mapped object phase inversion": "+",
   "highlite": 0
  },
  {
   "Object": "/mcs4_core_i4004_sp_board_dram_array_reg[1][6]/U$1",
   "Type": "DFF",
   "Mapping": "/mcs4_core_i4004_sp_board_dram_array_reg[1][6]/U$1",
   "Phase": "+",
   "User Setup object phase inversion": "+",
   "User Setup mapped object phase inversion": "+",
   "highlite": 0
  },
  {
   "Object": "/mcs4_core_i4004_sp_board_dram_array_reg[1][7]/U$1",
   "Type": "DFF",
   "Mapping": "/mcs4_core_i4004_sp_board_dram_array_reg[1][7]/U$1",
   "Phase": "+",
   "User Setup object phase inversion": "+",
   "User Setup mapped object phase inversion": "+",
   "highlite": 0
  },
  {
   "Object": "/mcs4_core_i4004_sp_board_dram_array_reg[2][0]/U$1",
   "Type": "DFF",
   "Mapping": "/mcs4_core_i4004_sp_board_dram_array_reg[2][0]/U$1",
   "Phase": "+",
   "User Setup object phase inversion": "+",
   "User Setup mapped object phase inversion": "+",
   "highlite": 0
  },
  {
   "Object": "/mcs4_core_i4004_sp_board_dram_array_reg[2][1]/U$1",
   "Type": "DFF",
   "Mapping": "/mcs4_core_i4004_sp_board_dram_array_reg[2][1]/U$1",
   "Phase": "+",
   "User Setup object phase inversion": "+",
   "User Setup mapped object phase inversion": "+",
   "highlite": 0
  },
  {
   "Object": "/mcs4_core_i4004_sp_board_dram_array_reg[2][2]/U$1",
   "Type": "DFF",
   "Mapping": "/mcs4_core_i4004_sp_board_dram_array_reg[2][2]/U$1",
   "Phase": "+",
   "User Setup object phase inversion": "+",
   "User Setup mapped object phase inversion": "+",
   "highlite": 0
  },
  {
   "Object": "/mcs4_core_i4004_sp_board_dram_array_reg[2][3]/U$1",
   "Type": "DFF",
   "Mapping": "/mcs4_core_i4004_sp_board_dram_array_reg[2][3]/U$1",
   "Phase": "+",
   "User Setup object phase inversion": "+",
   "User Setup mapped object phase inversion": "+",
   "highlite": 0
  },
  {
   "Object": "/mcs4_core_i4004_sp_board_dram_array_reg[2][4]/U$1",
   "Type": "DFF",
   "Mapping": "/mcs4_core_i4004_sp_board_dram_array_reg[2][4]/U$1",
   "Phase": "+",
   "User Setup object phase inversion": "+",
   "User Setup mapped object phase inversion": "+",
   "highlite": 0
  },
  {
   "Object": "/mcs4_core_i4004_sp_board_dram_array_reg[2][5]/U$1",
   "Type": "DFF",
   "Mapping": "/mcs4_core_i4004_sp_board_dram_array_reg[2][5]/U$1",
   "Phase": "+",
   "User Setup object phase inversion": "+",
   "User Setup mapped object phase inversion": "+",
   "highlite": 0
  },
  {
   "Object": "/mcs4_core_i4004_sp_board_dram_array_reg[2][6]/U$1",
   "Type": "DFF",
   "Mapping": "/mcs4_core_i4004_sp_board_dram_array_reg[2][6]/U$1",
   "Phase": "+",
   "User Setup object phase inversion": "+",
   "User Setup mapped object phase inversion": "+",
   "highlite": 0
  },
  {
   "Object": "/mcs4_core_i4004_sp_board_dram_array_reg[2][7]/U$1",
   "Type": "DFF",
   "Mapping": "/mcs4_core_i4004_sp_board_dram_array_reg[2][7]/U$1",
   "Phase": "+",
   "User Setup object phase inversion": "+",
   "User Setup mapped object phase inversion": "+",
   "highlite": 0
  },
  {
   "Object": "/mcs4_core_i4004_sp_board_dram_array_reg[3][0]/U$1",
   "Type": "DFF",
   "Mapping": "/mcs4_core_i4004_sp_board_dram_array_reg[3][0]/U$1",
   "Phase": "+",
   "User Setup object phase inversion": "+",
   "User Setup mapped object phase inversion": "+",
   "highlite": 0
  },
  {
   "Object": "/mcs4_core_i4004_sp_board_dram_array_reg[3][1]/U$1",
   "Type": "DFF",
   "Mapping": "/mcs4_core_i4004_sp_board_dram_array_reg[3][1]/U$1",
   "Phase": "+",
   "User Setup object phase inversion": "+",
   "User Setup mapped object phase inversion": "+",
   "highlite": 0
  },
  {
   "Object": "/mcs4_core_i4004_sp_board_dram_array_reg[3][2]/U$1",
   "Type": "DFF",
   "Mapping": "/mcs4_core_i4004_sp_board_dram_array_reg[3][2]/U$1",
   "Phase": "+",
   "User Setup object phase inversion": "+",
   "User Setup mapped object phase inversion": "+",
   "highlite": 0
  },
  {
   "Object": "/mcs4_core_i4004_sp_board_dram_array_reg[3][3]/U$1",
   "Type": "DFF",
   "Mapping": "/mcs4_core_i4004_sp_board_dram_array_reg[3][3]/U$1",
   "Phase": "+",
   "User Setup object phase inversion": "+",
   "User Setup mapped object phase inversion": "+",
   "highlite": 0
  },
  {
   "Object": "/mcs4_core_i4004_sp_board_dram_array_reg[3][4]/U$1",
   "Type": "DFF",
   "Mapping": "/mcs4_core_i4004_sp_board_dram_array_reg[3][4]/U$1",
   "Phase": "+",
   "User Setup object phase inversion": "+",
   "User Setup mapped object phase inversion": "+",
   "highlite": 0
  },
  {
   "Object": "/mcs4_core_i4004_sp_board_dram_array_reg[3][5]/U$1",
   "Type": "DFF",
   "Mapping": "/mcs4_core_i4004_sp_board_dram_array_reg[3][5]/U$1",
   "Phase": "+",
   "User Setup object phase inversion": "+",
   "User Setup mapped object phase inversion": "+",
   "highlite": 0
  },
  {
   "Object": "/mcs4_core_i4004_sp_board_dram_array_reg[3][6]/U$1",
   "Type": "DFF",
   "Mapping": "/mcs4_core_i4004_sp_board_dram_array_reg[3][6]/U$1",
   "Phase": "+",
   "User Setup object phase inversion": "+",
   "User Setup mapped object phase inversion": "+",
   "highlite": 0
  },
  {
   "Object": "/mcs4_core_i4004_sp_board_dram_array_reg[3][7]/U$1",
   "Type": "DFF",
   "Mapping": "/mcs4_core_i4004_sp_board_dram_array_reg[3][7]/U$1",
   "Phase": "+",
   "User Setup object phase inversion": "+",
   "User Setup mapped object phase inversion": "+",
   "highlite": 0
  },
  {
   "Object": "/mcs4_core_i4004_sp_board_dram_array_reg[4][0]/U$1",
   "Type": "DFF",
   "Mapping": "/mcs4_core_i4004_sp_board_dram_array_reg[4][0]/U$1",
   "Phase": "+",
   "User Setup object phase inversion": "+",
   "User Setup mapped object phase inversion": "+",
   "highlite": 0
  },
  {
   "Object": "/mcs4_core_i4004_sp_board_dram_array_reg[4][1]/U$1",
   "Type": "DFF",
   "Mapping": "/mcs4_core_i4004_sp_board_dram_array_reg[4][1]/U$1",
   "Phase": "+",
   "User Setup object phase inversion": "+",
   "User Setup mapped object phase inversion": "+",
   "highlite": 0
  },
  {
   "Object": "/mcs4_core_i4004_sp_board_dram_array_reg[4][2]/U$1",
   "Type": "DFF",
   "Mapping": "/mcs4_core_i4004_sp_board_dram_array_reg[4][2]/U$1",
   "Phase": "+",
   "User Setup object phase inversion": "+",
   "User Setup mapped object phase inversion": "+",
   "highlite": 0
  },
  {
   "Object": "/mcs4_core_i4004_sp_board_dram_array_reg[4][3]/U$1",
   "Type": "DFF",
   "Mapping": "/mcs4_core_i4004_sp_board_dram_array_reg[4][3]/U$1",
   "Phase": "+",
   "User Setup object phase inversion": "+",
   "User Setup mapped object phase inversion": "+",
   "highlite": 0
  },
  {
   "Object": "/mcs4_core_i4004_sp_board_dram_array_reg[4][4]/U$1",
   "Type": "DFF",
   "Mapping": "/mcs4_core_i4004_sp_board_dram_array_reg[4][4]/U$1",
   "Phase": "+",
   "User Setup object phase inversion": "+",
   "User Setup mapped object phase inversion": "+",
   "highlite": 0
  },
  {
   "Object": "/mcs4_core_i4004_sp_board_dram_array_reg[4][5]/U$1",
   "Type": "DFF",
   "Mapping": "/mcs4_core_i4004_sp_board_dram_array_reg[4][5]/U$1",
   "Phase": "+",
   "User Setup object phase inversion": "+",
   "User Setup mapped object phase inversion": "+",
   "highlite": 0
  },
  {
   "Object": "/mcs4_core_i4004_sp_board_dram_array_reg[4][6]/U$1",
   "Type": "DFF",
   "Mapping": "/mcs4_core_i4004_sp_board_dram_array_reg[4][6]/U$1",
   "Phase": "+",
   "User Setup object phase inversion": "+",
   "User Setup mapped object phase inversion": "+",
   "highlite": 0
  },
  {
   "Object": "/mcs4_core_i4004_sp_board_dram_array_reg[4][7]/U$1",
   "Type": "DFF",
   "Mapping": "/mcs4_core_i4004_sp_board_dram_array_reg[4][7]/U$1",
   "Phase": "+",
   "User Setup object phase inversion": "+",
   "User Setup mapped object phase inversion": "+",
   "highlite": 0
  },
  {
   "Object": "/mcs4_core_i4004_sp_board_dram_array_reg[5][0]/U$1",
   "Type": "DFF",
   "Mapping": "/mcs4_core_i4004_sp_board_dram_array_reg[5][0]/U$1",
   "Phase": "+",
   "User Setup object phase inversion": "+",
   "User Setup mapped object phase inversion": "+",
   "highlite": 0
  },
  {
   "Object": "/mcs4_core_i4004_sp_board_dram_array_reg[5][1]/U$1",
   "Type": "DFF",
   "Mapping": "/mcs4_core_i4004_sp_board_dram_array_reg[5][1]/U$1",
   "Phase": "+",
   "User Setup object phase inversion": "+",
   "User Setup mapped object phase inversion": "+",
   "highlite": 0
  },
  {
   "Object": "/mcs4_core_i4004_sp_board_dram_array_reg[5][2]/U$1",
   "Type": "DFF",
   "Mapping": "/mcs4_core_i4004_sp_board_dram_array_reg[5][2]/U$1",
   "Phase": "+",
   "User Setup object phase inversion": "+",
   "User Setup mapped object phase inversion": "+",
   "highlite": 0
  },
  {
   "Object": "/mcs4_core_i4004_sp_board_dram_array_reg[5][3]/U$1",
   "Type": "DFF",
   "Mapping": "/mcs4_core_i4004_sp_board_dram_array_reg[5][3]/U$1",
   "Phase": "+",
   "User Setup object phase inversion": "+",
   "User Setup mapped object phase inversion": "+",
   "highlite": 0
  },
  {
   "Object": "/mcs4_core_i4004_sp_board_dram_array_reg[5][4]/U$1",
   "Type": "DFF",
   "Mapping": "/mcs4_core_i4004_sp_board_dram_array_reg[5][4]/U$1",
   "Phase": "+",
   "User Setup object phase inversion": "+",
   "User Setup mapped object phase inversion": "+",
   "highlite": 0
  },
  {
   "Object": "/mcs4_core_i4004_sp_board_dram_array_reg[5][5]/U$1",
   "Type": "DFF",
   "Mapping": "/mcs4_core_i4004_sp_board_dram_array_reg[5][5]/U$1",
   "Phase": "+",
   "User Setup object phase inversion": "+",
   "User Setup mapped object phase inversion": "+",
   "highlite": 0
  },
  {
   "Object": "/mcs4_core_i4004_sp_board_dram_array_reg[5][6]/U$1",
   "Type": "DFF",
   "Mapping": "/mcs4_core_i4004_sp_board_dram_array_reg[5][6]/U$1",
   "Phase": "+",
   "User Setup object phase inversion": "+",
   "User Setup mapped object phase inversion": "+",
   "highlite": 0
  },
  {
   "Object": "/mcs4_core_i4004_sp_board_dram_array_reg[5][7]/U$1",
   "Type": "DFF",
   "Mapping": "/mcs4_core_i4004_sp_board_dram_array_reg[5][7]/U$1",
   "Phase": "+",
   "User Setup object phase inversion": "+",
   "User Setup mapped object phase inversion": "+",
   "highlite": 0
  },
  {
   "Object": "/mcs4_core_i4004_sp_board_dram_array_reg[6][0]/U$1",
   "Type": "DFF",
   "Mapping": "/mcs4_core_i4004_sp_board_dram_array_reg[6][0]/U$1",
   "Phase": "+",
   "User Setup object phase inversion": "+",
   "User Setup mapped object phase inversion": "+",
   "highlite": 0
  },
  {
   "Object": "/mcs4_core_i4004_sp_board_dram_array_reg[6][1]/U$1",
   "Type": "DFF",
   "Mapping": "/mcs4_core_i4004_sp_board_dram_array_reg[6][1]/U$1",
   "Phase": "+",
   "User Setup object phase inversion": "+",
   "User Setup mapped object phase inversion": "+",
   "highlite": 0
  },
  {
   "Object": "/mcs4_core_i4004_sp_board_dram_array_reg[6][2]/U$1",
   "Type": "DFF",
   "Mapping": "/mcs4_core_i4004_sp_board_dram_array_reg[6][2]/U$1",
   "Phase": "+",
   "User Setup object phase inversion": "+",
   "User Setup mapped object phase inversion": "+",
   "highlite": 0
  },
  {
   "Object": "/mcs4_core_i4004_sp_board_dram_array_reg[6][3]/U$1",
   "Type": "DFF",
   "Mapping": "/mcs4_core_i4004_sp_board_dram_array_reg[6][3]/U$1",
   "Phase": "+",
   "User Setup object phase inversion": "+",
   "User Setup mapped object phase inversion": "+",
   "highlite": 0
  },
  {
   "Object": "/mcs4_core_i4004_sp_board_dram_array_reg[6][4]/U$1",
   "Type": "DFF",
   "Mapping": "/mcs4_core_i4004_sp_board_dram_array_reg[6][4]/U$1",
   "Phase": "+",
   "User Setup object phase inversion": "+",
   "User Setup mapped object phase inversion": "+",
   "highlite": 0
  },
  {
   "Object": "/mcs4_core_i4004_sp_board_dram_array_reg[6][5]/U$1",
   "Type": "DFF",
   "Mapping": "/mcs4_core_i4004_sp_board_dram_array_reg[6][5]/U$1",
   "Phase": "+",
   "User Setup object phase inversion": "+",
   "User Setup mapped object phase inversion": "+",
   "highlite": 0
  },
  {
   "Object": "/mcs4_core_i4004_sp_board_dram_array_reg[6][6]/U$1",
   "Type": "DFF",
   "Mapping": "/mcs4_core_i4004_sp_board_dram_array_reg[6][6]/U$1",
   "Phase": "+",
   "User Setup object phase inversion": "+",
   "User Setup mapped object phase inversion": "+",
   "highlite": 0
  },
  {
   "Object": "/mcs4_core_i4004_sp_board_dram_array_reg[6][7]/U$1",
   "Type": "DFF",
   "Mapping": "/mcs4_core_i4004_sp_board_dram_array_reg[6][7]/U$1",
   "Phase": "+",
   "User Setup object phase inversion": "+",
   "User Setup mapped object phase inversion": "+",
   "highlite": 0
  },
  {
   "Object": "/mcs4_core_i4004_sp_board_dram_array_reg[7][0]/U$1",
   "Type": "DFF",
   "Mapping": "/mcs4_core_i4004_sp_board_dram_array_reg[7][0]/U$1",
   "Phase": "+",
   "User Setup object phase inversion": "+",
   "User Setup mapped object phase inversion": "+",
   "highlite": 0
  },
  {
   "Object": "/mcs4_core_i4004_sp_board_dram_array_reg[7][1]/U$1",
   "Type": "DFF",
   "Mapping": "/mcs4_core_i4004_sp_board_dram_array_reg[7][1]/U$1",
   "Phase": "+",
   "User Setup object phase inversion": "+",
   "User Setup mapped object phase inversion": "+",
   "highlite": 0
  },
  {
   "Object": "/mcs4_core_i4004_sp_board_dram_array_reg[7][2]/U$1",
   "Type": "DFF",
   "Mapping": "/mcs4_core_i4004_sp_board_dram_array_reg[7][2]/U$1",
   "Phase": "+",
   "User Setup object phase inversion": "+",
   "User Setup mapped object phase inversion": "+",
   "highlite": 0
  },
  {
   "Object": "/mcs4_core_i4004_sp_board_dram_array_reg[7][3]/U$1",
   "Type": "DFF",
   "Mapping": "/mcs4_core_i4004_sp_board_dram_array_reg[7][3]/U$1",
   "Phase": "+",
   "User Setup object phase inversion": "+",
   "User Setup mapped object phase inversion": "+",
   "highlite": 0
  },
  {
   "Object": "/mcs4_core_i4004_sp_board_dram_array_reg[7][4]/U$1",
   "Type": "DFF",
   "Mapping": "/mcs4_core_i4004_sp_board_dram_array_reg[7][4]/U$1",
   "Phase": "+",
   "User Setup object phase inversion": "+",
   "User Setup mapped object phase inversion": "+",
   "highlite": 0
  },
  {
   "Object": "/mcs4_core_i4004_sp_board_dram_array_reg[7][5]/U$1",
   "Type": "DFF",
   "Mapping": "/mcs4_core_i4004_sp_board_dram_array_reg[7][5]/U$1",
   "Phase": "+",
   "User Setup object phase inversion": "+",
   "User Setup mapped object phase inversion": "+",
   "highlite": 0
  },
  {
   "Object": "/mcs4_core_i4004_sp_board_dram_array_reg[7][6]/U$1",
   "Type": "DFF",
   "Mapping": "/mcs4_core_i4004_sp_board_dram_array_reg[7][6]/U$1",
   "Phase": "+",
   "User Setup object phase inversion": "+",
   "User Setup mapped object phase inversion": "+",
   "highlite": 0
  },
  {
   "Object": "/mcs4_core_i4004_sp_board_dram_array_reg[7][7]/U$1",
   "Type": "DFF",
   "Mapping": "/mcs4_core_i4004_sp_board_dram_array_reg[7][7]/U$1",
   "Phase": "+",
   "User Setup object phase inversion": "+",
   "User Setup mapped object phase inversion": "+",
   "highlite": 0
  },
  {
   "Object": "/mcs4_core_i4004_sp_board_dram_temp_reg[0]/U$1",
   "Type": "DFF",
   "Mapping": "/mcs4_core_i4004_sp_board_dram_temp_reg[0]/U$1",
   "Phase": "+",
   "User Setup object phase inversion": "+",
   "User Setup mapped object phase inversion": "+",
   "highlite": 0
  },
  {
   "Object": "/mcs4_core_i4004_sp_board_dram_temp_reg[1]/U$1",
   "Type": "DFF",
   "Mapping": "/mcs4_core_i4004_sp_board_dram_temp_reg[1]/U$1",
   "Phase": "+",
   "User Setup object phase inversion": "+",
   "User Setup mapped object phase inversion": "+",
   "highlite": 0
  },
  {
   "Object": "/mcs4_core_i4004_sp_board_dram_temp_reg[2]/U$1",
   "Type": "DFF",
   "Mapping": "/mcs4_core_i4004_sp_board_dram_temp_reg[2]/U$1",
   "Phase": "+",
   "User Setup object phase inversion": "+",
   "User Setup mapped object phase inversion": "+",
   "highlite": 0
  },
  {
   "Object": "/mcs4_core_i4004_sp_board_dram_temp_reg[3]/U$1",
   "Type": "DFF",
   "Mapping": "/mcs4_core_i4004_sp_board_dram_temp_reg[3]/U$1",
   "Phase": "+",
   "User Setup object phase inversion": "+",
   "User Setup mapped object phase inversion": "+",
   "highlite": 0
  },
  {
   "Object": "/mcs4_core_i4004_sp_board_dram_temp_reg[4]/U$1",
   "Type": "DFF",
   "Mapping": "/mcs4_core_i4004_sp_board_dram_temp_reg[4]/U$1",
   "Phase": "+",
   "User Setup object phase inversion": "+",
   "User Setup mapped object phase inversion": "+",
   "highlite": 0
  },
  {
   "Object": "/mcs4_core_i4004_sp_board_dram_temp_reg[5]/U$1",
   "Type": "DFF",
   "Mapping": "/mcs4_core_i4004_sp_board_dram_temp_reg[5]/U$1",
   "Phase": "+",
   "User Setup object phase inversion": "+",
   "User Setup mapped object phase inversion": "+",
   "highlite": 0
  },
  {
   "Object": "/mcs4_core_i4004_sp_board_dram_temp_reg[6]/U$1",
   "Type": "DFF",
   "Mapping": "/mcs4_core_i4004_sp_board_dram_temp_reg[6]/U$1",
   "Phase": "+",
   "User Setup object phase inversion": "+",
   "User Setup mapped object phase inversion": "+",
   "highlite": 0
  },
  {
   "Object": "/mcs4_core_i4004_sp_board_dram_temp_reg[7]/U$1",
   "Type": "DFF",
   "Mapping": "/mcs4_core_i4004_sp_board_dram_temp_reg[7]/U$1",
   "Phase": "+",
   "User Setup object phase inversion": "+",
   "User Setup mapped object phase inversion": "+",
   "highlite": 0
  },
  {
   "Object": "/mcs4_core_i4004_sp_board_n0592_reg/U$1",
   "Type": "DFF",
   "Mapping": "/mcs4_core_i4004_sp_board_n0592_reg/U$1",
   "Phase": "+",
   "User Setup object phase inversion": "+",
   "User Setup mapped object phase inversion": "+",
   "highlite": 0
  },
  {
   "Object": "/mcs4_core_i4004_sp_board_n0615_reg/U$1",
   "Type": "DFF",
   "Mapping": "/mcs4_core_i4004_sp_board_n0615_reg/U$1",
   "Phase": "+",
   "User Setup object phase inversion": "+",
   "User Setup mapped object phase inversion": "+",
   "highlite": 0
  },
  {
   "Object": "/mcs4_core_i4004_sp_board_reg_rfsh_0_master_reg/U$1",
   "Type": "DFF",
   "Mapping": "/mcs4_core_i4004_sp_board_reg_rfsh_0_master_reg/U$1",
   "Phase": "+",
   "User Setup object phase inversion": "+",
   "User Setup mapped object phase inversion": "+",
   "highlite": 0
  },
  {
   "Object": "/mcs4_core_i4004_sp_board_reg_rfsh_0_slave_reg/U$1",
   "Type": "DFF",
   "Mapping": "/mcs4_core_i4004_sp_board_reg_rfsh_0_slave_reg/U$1",
   "Phase": "+",
   "User Setup object phase inversion": "+",
   "User Setup mapped object phase inversion": "+",
   "highlite": 0
  },
  {
   "Object": "/mcs4_core_i4004_sp_board_reg_rfsh_1_master_reg/U$1",
   "Type": "DFF",
   "Mapping": "/mcs4_core_i4004_sp_board_reg_rfsh_1_master_reg/U$1",
   "Phase": "+",
   "User Setup object phase inversion": "+",
   "User Setup mapped object phase inversion": "+",
   "highlite": 0
  },
  {
   "Object": "/mcs4_core_i4004_sp_board_reg_rfsh_1_slave_reg/U$1",
   "Type": "DFF",
   "Mapping": "/mcs4_core_i4004_sp_board_reg_rfsh_1_slave_reg/U$1",
   "Phase": "+",
   "User Setup object phase inversion": "+",
   "User Setup mapped object phase inversion": "+",
   "highlite": 0
  },
  {
   "Object": "/mcs4_core_i4004_sp_board_reg_rfsh_2_master_reg/U$1",
   "Type": "DFF",
   "Mapping": "/mcs4_core_i4004_sp_board_reg_rfsh_2_master_reg/U$1",
   "Phase": "+",
   "User Setup object phase inversion": "+",
   "User Setup mapped object phase inversion": "+",
   "highlite": 0
  },
  {
   "Object": "/mcs4_core_i4004_sp_board_reg_rfsh_2_slave_reg/U$1",
   "Type": "DFF",
   "Mapping": "/mcs4_core_i4004_sp_board_reg_rfsh_2_slave_reg/U$1",
   "Phase": "+",
   "User Setup object phase inversion": "+",
   "User Setup mapped object phase inversion": "+",
   "highlite": 0
  },
  {
   "Object": "/mcs4_core_i4004_tio_board_n0278_reg/U$1",
   "Type": "DFF",
   "Mapping": "/mcs4_core_i4004_tio_board_n0278_reg/U$1",
   "Phase": "+",
   "User Setup object phase inversion": "+",
   "User Setup mapped object phase inversion": "+",
   "highlite": 0
  },
  {
   "Object": "/mcs4_core_i4004_tio_board_n0685_reg/U$1",
   "Type": "DFF",
   "Mapping": "/mcs4_core_i4004_tio_board_n0685_reg/U$1",
   "Phase": "+",
   "User Setup object phase inversion": "+",
   "User Setup mapped object phase inversion": "+",
   "highlite": 0
  },
  {
   "Object": "/mcs4_core_i4004_tio_board_n0699_reg/U$1",
   "Type": "DFF",
   "Mapping": "/mcs4_core_i4004_tio_board_n0699_reg/U$1",
   "Phase": "+",
   "User Setup object phase inversion": "+",
   "User Setup mapped object phase inversion": "+",
   "highlite": 0
  },
  {
   "Object": "/mcs4_core_i4004_tio_board_n0707_reg/U$1",
   "Type": "DFF",
   "Mapping": "/mcs4_core_i4004_tio_board_n0707_reg/U$1",
   "Phase": "+",
   "User Setup object phase inversion": "+",
   "User Setup mapped object phase inversion": "+",
   "highlite": 0
  },
  {
   "Object": "/mcs4_core_i4004_tio_board_timing_generator_a11_reg/U$1",
   "Type": "DFF",
   "Mapping": "/mcs4_core_i4004_tio_board_timing_generator_a11_reg/U$1",
   "Phase": "+",
   "User Setup object phase inversion": "+",
   "User Setup mapped object phase inversion": "+",
   "highlite": 0
  },
  {
   "Object": "/mcs4_core_i4004_tio_board_timing_generator_a21_reg/U$1",
   "Type": "DFF",
   "Mapping": "/mcs4_core_i4004_tio_board_timing_generator_a21_reg/U$1",
   "Phase": "+",
   "User Setup object phase inversion": "+",
   "User Setup mapped object phase inversion": "+",
   "highlite": 0
  },
  {
   "Object": "/mcs4_core_i4004_tio_board_timing_generator_a31_reg/U$1",
   "Type": "DFF",
   "Mapping": "/mcs4_core_i4004_tio_board_timing_generator_a31_reg/U$1",
   "Phase": "+",
   "User Setup object phase inversion": "+",
   "User Setup mapped object phase inversion": "+",
   "highlite": 0
  },
  {
   "Object": "/mcs4_core_i4004_tio_board_timing_generator_m11_reg/U$1",
   "Type": "DFF",
   "Mapping": "/mcs4_core_i4004_tio_board_timing_generator_m11_reg/U$1",
   "Phase": "+",
   "User Setup object phase inversion": "+",
   "User Setup mapped object phase inversion": "+",
   "highlite": 0
  },
  {
   "Object": "/mcs4_core_i4004_tio_board_timing_generator_m21_reg/U$1",
   "Type": "DFF",
   "Mapping": "/mcs4_core_i4004_tio_board_timing_generator_m21_reg/U$1",
   "Phase": "+",
   "User Setup object phase inversion": "+",
   "User Setup mapped object phase inversion": "+",
   "highlite": 0
  },
  {
   "Object": "/mcs4_core_i4004_tio_board_timing_generator_sync_reg/U$1",
   "Type": "DFF",
   "Mapping": "/mcs4_core_i4004_tio_board_timing_generator_sync_reg/U$1",
   "Phase": "+",
   "User Setup object phase inversion": "+",
   "User Setup mapped object phase inversion": "+",
   "highlite": 0
  },
  {
   "Object": "/mcs4_core_i4004_tio_board_timing_generator_x11_reg/U$1",
   "Type": "DFF",
   "Mapping": "/mcs4_core_i4004_tio_board_timing_generator_x11_reg/U$1",
   "Phase": "+",
   "User Setup object phase inversion": "+",
   "User Setup mapped object phase inversion": "+",
   "highlite": 0
  },
  {
   "Object": "/mcs4_core_i4004_tio_board_timing_generator_x21_reg/U$1",
   "Type": "DFF",
   "Mapping": "/mcs4_core_i4004_tio_board_timing_generator_x21_reg/U$1",
   "Phase": "+",
   "User Setup object phase inversion": "+",
   "User Setup mapped object phase inversion": "+",
   "highlite": 0
  },
  {
   "Object": "/mcs4_core_i4004_tio_board_timing_generator_x22_reg/U$1",
   "Type": "DFF",
   "Mapping": "/mcs4_core_i4004_tio_board_timing_generator_x22_reg/U$1",
   "Phase": "+",
   "User Setup object phase inversion": "+",
   "User Setup mapped object phase inversion": "+",
   "highlite": 0
  },
  {
   "Object": "/mcs4_core_i4004_tio_board_timing_generator_x31_reg/U$1",
   "Type": "DFF",
   "Mapping": "/mcs4_core_i4004_tio_board_timing_generator_x31_reg/U$1",
   "Phase": "+",
   "User Setup object phase inversion": "+",
   "User Setup mapped object phase inversion": "+",
   "highlite": 0
  },
  {
   "Object": "/mcs4_core_ram_0_opa_reg[0]/U$1",
   "Type": "DFF",
   "Mapping": "/mcs4_core_ram_0_opa_reg[0]/U$1",
   "Phase": "+",
   "User Setup object phase inversion": "+",
   "User Setup mapped object phase inversion": "+",
   "highlite": 0
  },
  {
   "Object": "/mcs4_core_ram_0_opa_reg[1]/U$1",
   "Type": "DFF",
   "Mapping": "/mcs4_core_ram_0_opa_reg[1]/U$1",
   "Phase": "+",
   "User Setup object phase inversion": "+",
   "User Setup mapped object phase inversion": "+",
   "highlite": 0
  },
  {
   "Object": "/mcs4_core_ram_0_opa_reg[2]/U$1",
   "Type": "DFF",
   "Mapping": "/mcs4_core_ram_0_opa_reg[2]/U$1",
   "Phase": "+",
   "User Setup object phase inversion": "+",
   "User Setup mapped object phase inversion": "+",
   "highlite": 0
  },
  {
   "Object": "/mcs4_core_ram_0_opa_reg[3]/U$1",
   "Type": "DFF",
   "Mapping": "/mcs4_core_ram_0_opa_reg[3]/U$1",
   "Phase": "+",
   "User Setup object phase inversion": "+",
   "User Setup mapped object phase inversion": "+",
   "highlite": 0
  },
  {
   "Object": "/mcs4_core_ram_0_oport_reg[0]/U$1",
   "Type": "DFF",
   "Mapping": "/mcs4_core_ram_0_oport_reg[0]/U$1",
   "Phase": "+",
   "User Setup object phase inversion": "+",
   "User Setup mapped object phase inversion": "+",
   "highlite": 0
  },
  {
   "Object": "/mcs4_core_ram_0_ram_sel_reg/U$1",
   "Type": "DFF",
   "Mapping": "/mcs4_core_ram_0_ram_sel_reg/U$1",
   "Phase": "+",
   "User Setup object phase inversion": "+",
   "User Setup mapped object phase inversion": "+",
   "highlite": 0
  },
  {
   "Object": "/mcs4_core_ram_0_timing_recovery_a11_reg/U$1",
   "Type": "DFF",
   "Mapping": "/mcs4_core_ram_0_timing_recovery_a11_reg/U$1",
   "Phase": "+",
   "User Setup object phase inversion": "+",
   "User Setup mapped object phase inversion": "+",
   "highlite": 0
  },
  {
   "Object": "/mcs4_core_ram_0_timing_recovery_a12_reg/U$1",
   "Type": "DFF",
   "Mapping": "/mcs4_core_ram_0_timing_recovery_a12_reg/U$1",
   "Phase": "+",
   "User Setup object phase inversion": "+",
   "User Setup mapped object phase inversion": "+",
   "highlite": 0
  },
  {
   "Object": "/mcs4_core_ram_0_timing_recovery_a21_reg/U$1",
   "Type": "DFF",
   "Mapping": "/mcs4_core_ram_0_timing_recovery_a21_reg/U$1",
   "Phase": "+",
   "User Setup object phase inversion": "+",
   "User Setup mapped object phase inversion": "+",
   "highlite": 0
  },
  {
   "Object": "/mcs4_core_ram_0_timing_recovery_a22_reg/U$1",
   "Type": "DFF",
   "Mapping": "/mcs4_core_ram_0_timing_recovery_a22_reg/U$1",
   "Phase": "+",
   "User Setup object phase inversion": "+",
   "User Setup mapped object phase inversion": "+",
   "highlite": 0
  },
  {
   "Object": "/mcs4_core_ram_0_timing_recovery_a31_reg/U$1",
   "Type": "DFF",
   "Mapping": "/mcs4_core_ram_0_timing_recovery_a31_reg/U$1",
   "Phase": "+",
   "User Setup object phase inversion": "+",
   "User Setup mapped object phase inversion": "+",
   "highlite": 0
  },
  {
   "Object": "/mcs4_core_ram_0_timing_recovery_a32_reg/U$1",
   "Type": "DFF",
   "Mapping": "/mcs4_core_ram_0_timing_recovery_a32_reg/U$1",
   "Phase": "+",
   "User Setup object phase inversion": "+",
   "User Setup mapped object phase inversion": "+",
   "highlite": 0
  },
  {
   "Object": "/mcs4_core_ram_0_timing_recovery_m11_reg/U$1",
   "Type": "DFF",
   "Mapping": "/mcs4_core_ram_0_timing_recovery_m11_reg/U$1",
   "Phase": "+",
   "User Setup object phase inversion": "+",
   "User Setup mapped object phase inversion": "+",
   "highlite": 0
  },
  {
   "Object": "/mcs4_core_ram_0_timing_recovery_m12_reg/U$1",
   "Type": "DFF",
   "Mapping": "/mcs4_core_ram_0_timing_recovery_m12_reg/U$1",
   "Phase": "+",
   "User Setup object phase inversion": "+",
   "User Setup mapped object phase inversion": "+",
   "highlite": 0
  },
  {
   "Object": "/mcs4_core_ram_0_timing_recovery_m21_reg/U$1",
   "Type": "DFF",
   "Mapping": "/mcs4_core_ram_0_timing_recovery_m21_reg/U$1",
   "Phase": "+",
   "User Setup object phase inversion": "+",
   "User Setup mapped object phase inversion": "+",
   "highlite": 0
  },
  {
   "Object": "/mcs4_core_ram_0_timing_recovery_x11_reg/U$1",
   "Type": "DFF",
   "Mapping": "/mcs4_core_ram_0_timing_recovery_x11_reg/U$1",
   "Phase": "+",
   "User Setup object phase inversion": "+",
   "User Setup mapped object phase inversion": "+",
   "highlite": 0
  },
  {
   "Object": "/mcs4_core_ram_0_timing_recovery_x12_reg/U$1",
   "Type": "DFF",
   "Mapping": "/mcs4_core_ram_0_timing_recovery_x12_reg/U$1",
   "Phase": "+",
   "User Setup object phase inversion": "+",
   "User Setup mapped object phase inversion": "+",
   "highlite": 0
  },
  {
   "Object": "/mcs4_core_ram_0_timing_recovery_x21_reg/U$1",
   "Type": "DFF",
   "Mapping": "/mcs4_core_ram_0_timing_recovery_x21_reg/U$1",
   "Phase": "+",
   "User Setup object phase inversion": "+",
   "User Setup mapped object phase inversion": "+",
   "highlite": 0
  },
  {
   "Object": "/mcs4_core_rom_0_io_out_reg[0]/U$1",
   "Type": "DFF",
   "Mapping": "/mcs4_core_rom_0_io_out_reg[0]/U$1",
   "Phase": "+",
   "User Setup object phase inversion": "+",
   "User Setup mapped object phase inversion": "+",
   "highlite": 0
  },
  {
   "Object": "/mcs4_core_rom_0_io_out_reg[1]/U$1",
   "Type": "DFF",
   "Mapping": "/mcs4_core_rom_0_io_out_reg[1]/U$1",
   "Phase": "+",
   "User Setup object phase inversion": "+",
   "User Setup mapped object phase inversion": "+",
   "highlite": 0
  },
  {
   "Object": "/mcs4_core_rom_0_io_out_reg[2]/U$1",
   "Type": "DFF",
   "Mapping": "/mcs4_core_rom_0_io_out_reg[2]/U$1",
   "Phase": "+",
   "User Setup object phase inversion": "+",
   "User Setup mapped object phase inversion": "+",
   "highlite": 0
  },
  {
   "Object": "/mcs4_core_rom_0_io_out_reg[3]/U$1",
   "Type": "DFF",
   "Mapping": "/mcs4_core_rom_0_io_out_reg[3]/U$1",
   "Phase": "+",
   "User Setup object phase inversion": "+",
   "User Setup mapped object phase inversion": "+",
   "highlite": 0
  },
  {
   "Object": "/mcs4_core_rom_0_n0135_reg/U$1",
   "Type": "DFF",
   "Mapping": "/mcs4_core_rom_0_n0135_reg/U$1",
   "Phase": "+",
   "User Setup object phase inversion": "+",
   "User Setup mapped object phase inversion": "+",
   "highlite": 0
  },
  {
   "Object": "/mcs4_core_rom_0_srcff_reg/U$1",
   "Type": "DFF",
   "Mapping": "/mcs4_core_rom_0_srcff_reg/U$1",
   "Phase": "+",
   "User Setup object phase inversion": "+",
   "User Setup mapped object phase inversion": "+",
   "highlite": 0
  },
  {
   "Object": "/mcs4_core_rom_0_timing_recovery_a11_reg/U$1",
   "Type": "DFF",
   "Mapping": "/mcs4_core_rom_0_timing_recovery_a11_reg/U$1",
   "Phase": "+",
   "User Setup object phase inversion": "+",
   "User Setup mapped object phase inversion": "+",
   "highlite": 0
  },
  {
   "Object": "/mcs4_core_rom_0_timing_recovery_a21_reg/U$1",
   "Type": "DFF",
   "Mapping": "/mcs4_core_rom_0_timing_recovery_a21_reg/U$1",
   "Phase": "+",
   "User Setup object phase inversion": "+",
   "User Setup mapped object phase inversion": "+",
   "highlite": 0
  },
  {
   "Object": "/mcs4_core_rom_0_timing_recovery_a22_reg/U$1",
   "Type": "DFF",
   "Mapping": "/mcs4_core_rom_0_timing_recovery_a22_reg/U$1",
   "Phase": "+",
   "User Setup object phase inversion": "+",
   "User Setup mapped object phase inversion": "+",
   "highlite": 0
  },
  {
   "Object": "/mcs4_core_rom_0_timing_recovery_a31_reg/U$1",
   "Type": "DFF",
   "Mapping": "/mcs4_core_rom_0_timing_recovery_a31_reg/U$1",
   "Phase": "+",
   "User Setup object phase inversion": "+",
   "User Setup mapped object phase inversion": "+",
   "highlite": 0
  },
  {
   "Object": "/mcs4_core_rom_0_timing_recovery_a32_reg/U$1",
   "Type": "DFF",
   "Mapping": "/mcs4_core_rom_0_timing_recovery_a32_reg/U$1",
   "Phase": "+",
   "User Setup object phase inversion": "+",
   "User Setup mapped object phase inversion": "+",
   "highlite": 0
  },
  {
   "Object": "/mcs4_core_rom_0_timing_recovery_m11_reg/U$1",
   "Type": "DFF",
   "Mapping": "/mcs4_core_rom_0_timing_recovery_m11_reg/U$1",
   "Phase": "+",
   "User Setup object phase inversion": "+",
   "User Setup mapped object phase inversion": "+",
   "highlite": 0
  },
  {
   "Object": "/mcs4_core_rom_0_timing_recovery_m12_reg/U$1",
   "Type": "DFF",
   "Mapping": "/mcs4_core_rom_0_timing_recovery_m12_reg/U$1",
   "Phase": "+",
   "User Setup object phase inversion": "+",
   "User Setup mapped object phase inversion": "+",
   "highlite": 0
  },
  {
   "Object": "/mcs4_core_rom_0_timing_recovery_m21_reg/U$1",
   "Type": "DFF",
   "Mapping": "/mcs4_core_rom_0_timing_recovery_m21_reg/U$1",
   "Phase": "+",
   "User Setup object phase inversion": "+",
   "User Setup mapped object phase inversion": "+",
   "highlite": 0
  },
  {
   "Object": "/mcs4_core_rom_0_timing_recovery_m22_reg/U$1",
   "Type": "DFF",
   "Mapping": "/mcs4_core_rom_0_timing_recovery_m22_reg/U$1",
   "Phase": "+",
   "User Setup object phase inversion": "+",
   "User Setup mapped object phase inversion": "+",
   "highlite": 0
  },
  {
   "Object": "/mcs4_core_rom_0_timing_recovery_x11_reg/U$1",
   "Type": "DFF",
   "Mapping": "/mcs4_core_rom_0_timing_recovery_x11_reg/U$1",
   "Phase": "+",
   "User Setup object phase inversion": "+",
   "User Setup mapped object phase inversion": "+",
   "highlite": 0
  },
  {
   "Object": "/mcs4_core_rom_0_timing_recovery_x12_reg/U$1",
   "Type": "DFF",
   "Mapping": "/mcs4_core_rom_0_timing_recovery_x12_reg/U$1",
   "Phase": "+",
   "User Setup object phase inversion": "+",
   "User Setup mapped object phase inversion": "+",
   "highlite": 0
  },
  {
   "Object": "/mcs4_core_rom_0_timing_recovery_x21_reg/U$1",
   "Type": "DFF",
   "Mapping": "/mcs4_core_rom_0_timing_recovery_x21_reg/U$1",
   "Phase": "+",
   "User Setup object phase inversion": "+",
   "User Setup mapped object phase inversion": "+",
   "highlite": 0
  },
  {
   "Object": "/mcs4_core_rom_0_timing_recovery_x22_reg/U$1",
   "Type": "DFF",
   "Mapping": "/mcs4_core_rom_0_timing_recovery_x22_reg/U$1",
   "Phase": "+",
   "User Setup object phase inversion": "+",
   "User Setup mapped object phase inversion": "+",
   "highlite": 0
  },
  {
   "Object": "/mcs4_core_rom_1_chipsel_reg/U$1",
   "Type": "DFF",
   "Mapping": "/mcs4_core_rom_1_chipsel_reg/U$1",
   "Phase": "+",
   "User Setup object phase inversion": "+",
   "User Setup mapped object phase inversion": "+",
   "highlite": 0
  },
  {
   "Object": "/mcs4_core_rom_1_extbusdrive_reg/U$1",
   "Type": "DFF",
   "Mapping": "/mcs4_core_rom_1_extbusdrive_reg/U$1",
   "Phase": "+",
   "User Setup object phase inversion": "+",
   "User Setup mapped object phase inversion": "+",
   "highlite": 0
  },
  {
   "Object": "/mcs4_core_rom_1_io_out_reg[0]/U$1",
   "Type": "DFF",
   "Mapping": "/mcs4_core_rom_1_io_out_reg[0]/U$1",
   "Phase": "+",
   "User Setup object phase inversion": "+",
   "User Setup mapped object phase inversion": "+",
   "highlite": 0
  },
  {
   "Object": "/mcs4_core_rom_1_io_out_reg[1]/U$1",
   "Type": "DFF",
   "Mapping": "/mcs4_core_rom_1_io_out_reg[1]/U$1",
   "Phase": "+",
   "User Setup object phase inversion": "+",
   "User Setup mapped object phase inversion": "+",
   "highlite": 0
  },
  {
   "Object": "/mcs4_core_rom_1_io_out_reg[2]/U$1",
   "Type": "DFF",
   "Mapping": "/mcs4_core_rom_1_io_out_reg[2]/U$1",
   "Phase": "+",
   "User Setup object phase inversion": "+",
   "User Setup mapped object phase inversion": "+",
   "highlite": 0
  },
  {
   "Object": "/mcs4_core_rom_1_io_out_reg[3]/U$1",
   "Type": "DFF",
   "Mapping": "/mcs4_core_rom_1_io_out_reg[3]/U$1",
   "Phase": "+",
   "User Setup object phase inversion": "+",
   "User Setup mapped object phase inversion": "+",
   "highlite": 0
  },
  {
   "Object": "/mcs4_core_rom_1_n0135_reg/U$1",
   "Type": "DFF",
   "Mapping": "/mcs4_core_rom_1_n0135_reg/U$1",
   "Phase": "+",
   "User Setup object phase inversion": "+",
   "User Setup mapped object phase inversion": "+",
   "highlite": 0
  },
  {
   "Object": "/mcs4_core_rom_1_n0161_reg/U$1",
   "Type": "DFF",
   "Mapping": "/mcs4_core_rom_1_n0161_reg/U$1",
   "Phase": "+",
   "User Setup object phase inversion": "+",
   "User Setup mapped object phase inversion": "+",
   "highlite": 0
  },
  {
   "Object": "/mcs4_core_rom_1_srcff_reg/U$1",
   "Type": "DFF",
   "Mapping": "/mcs4_core_rom_1_srcff_reg/U$1",
   "Phase": "+",
   "User Setup object phase inversion": "+",
   "User Setup mapped object phase inversion": "+",
   "highlite": 0
  },
  {
   "Object": "/mcs4_core_shiftreg_cp_delay_reg[1]/U$1",
   "Type": "DFF",
   "Mapping": "/mcs4_core_shiftreg_cp_delay_reg[1]/U$1",
   "Phase": "+",
   "User Setup object phase inversion": "+",
   "User Setup mapped object phase inversion": "+",
   "highlite": 0
  },
  {
   "Object": "/mcs4_core_shiftreg_cp_delay_reg[2]/U$1",
   "Type": "DFF",
   "Mapping": "/mcs4_core_shiftreg_cp_delay_reg[2]/U$1",
   "Phase": "+",
   "User Setup object phase inversion": "+",
   "User Setup mapped object phase inversion": "+",
   "highlite": 0
  },
  {
   "Object": "/mcs4_core_shiftreg_cp_delay_reg[3]/U$1",
   "Type": "DFF",
   "Mapping": "/mcs4_core_shiftreg_cp_delay_reg[3]/U$1",
   "Phase": "+",
   "User Setup object phase inversion": "+",
   "User Setup mapped object phase inversion": "+",
   "highlite": 0
  },
  {
   "Object": "/mcs4_core_shiftreg_cp_delayed_reg/U$1",
   "Type": "DFF",
   "Mapping": "/mcs4_core_shiftreg_cp_delayed_reg/U$1",
   "Phase": "+",
   "User Setup object phase inversion": "+",
   "User Setup mapped object phase inversion": "+",
   "highlite": 0
  },
  {
   "Object": "/mcs4_core_shiftreg_shifter_reg[0]/U$1",
   "Type": "DFF",
   "Mapping": "/mcs4_core_shiftreg_shifter_reg[0]/U$1",
   "Phase": "+",
   "User Setup object phase inversion": "+",
   "User Setup mapped object phase inversion": "+",
   "highlite": 0
  },
  {
   "Object": "/mcs4_core_shiftreg_shifter_reg[1]/U$1",
   "Type": "DFF",
   "Mapping": "/mcs4_core_shiftreg_shifter_reg[1]/U$1",
   "Phase": "+",
   "User Setup object phase inversion": "+",
   "User Setup mapped object phase inversion": "+",
   "highlite": 0
  },
  {
   "Object": "/mcs4_core_shiftreg_shifter_reg[2]/U$1",
   "Type": "DFF",
   "Mapping": "/mcs4_core_shiftreg_shifter_reg[2]/U$1",
   "Phase": "+",
   "User Setup object phase inversion": "+",
   "User Setup mapped object phase inversion": "+",
   "highlite": 0
  },
  {
   "Object": "/mcs4_core_shiftreg_shifter_reg[3]/U$1",
   "Type": "DFF",
   "Mapping": "/mcs4_core_shiftreg_shifter_reg[3]/U$1",
   "Phase": "+",
   "User Setup object phase inversion": "+",
   "User Setup mapped object phase inversion": "+",
   "highlite": 0
  },
  {
   "Object": "/mcs4_core_shiftreg_shifter_reg[4]/U$1",
   "Type": "DFF",
   "Mapping": "/mcs4_core_shiftreg_shifter_reg[4]/U$1",
   "Phase": "+",
   "User Setup object phase inversion": "+",
   "User Setup mapped object phase inversion": "+",
   "highlite": 0
  },
  {
   "Object": "/mcs4_core_shiftreg_shifter_reg[5]/U$1",
   "Type": "DFF",
   "Mapping": "/mcs4_core_shiftreg_shifter_reg[5]/U$1",
   "Phase": "+",
   "User Setup object phase inversion": "+",
   "User Setup mapped object phase inversion": "+",
   "highlite": 0
  },
  {
   "Object": "/mcs4_core_shiftreg_shifter_reg[6]/U$1",
   "Type": "DFF",
   "Mapping": "/mcs4_core_shiftreg_shifter_reg[6]/U$1",
   "Phase": "+",
   "User Setup object phase inversion": "+",
   "User Setup mapped object phase inversion": "+",
   "highlite": 0
  },
  {
   "Object": "/mcs4_core_shiftreg_shifter_reg[7]/U$1",
   "Type": "DFF",
   "Mapping": "/mcs4_core_shiftreg_shifter_reg[7]/U$1",
   "Phase": "+",
   "User Setup object phase inversion": "+",
   "User Setup mapped object phase inversion": "+",
   "highlite": 0
  },
  {
   "Object": "/mcs4_core_shiftreg_shifter_reg[8]/U$1",
   "Type": "DFF",
   "Mapping": "/mcs4_core_shiftreg_shifter_reg[8]/U$1",
   "Phase": "+",
   "User Setup object phase inversion": "+",
   "User Setup mapped object phase inversion": "+",
   "highlite": 0
  },
  {
   "Object": "/mcs4_core_shiftreg_shifter_reg[9]/U$1",
   "Type": "DFF",
   "Mapping": "/mcs4_core_shiftreg_shifter_reg[9]/U$1",
   "Phase": "+",
   "User Setup object phase inversion": "+",
   "User Setup mapped object phase inversion": "+",
   "highlite": 0
  },
  {
   "Object": "/mcs4_core_i4004_alu_board_n0550_reg/U$1",
   "Type": "DFF",
   "Mapping": "/mcs4_core_i4004_alu_board_n0550_reg/U$1",
   "Phase": "+",
   "User Setup object phase inversion": "+",
   "User Setup mapped object phase inversion": "+",
   "highlite": 0
  },
  {
   "Object": "/mcs4_core_i4004_alu_board_acc_out_reg[3]/U$1",
   "Type": "DFF",
   "Mapping": "/mcs4_core_i4004_alu_board_acc_out_reg[3]/U$1",
   "Phase": "+",
   "User Setup object phase inversion": "+",
   "User Setup mapped object phase inversion": "+",
   "highlite": 0
  },
  {
   "Object": "/mcs4_core_clockgen_clockdiv_reg[2]/U$1",
   "Type": "DFF",
   "Mapping": "/mcs4_core_clockgen_clockdiv_reg[2]/U$1",
   "Phase": "+",
   "User Setup object phase inversion": "+",
   "User Setup mapped object phase inversion": "+",
   "highlite": 0
  },
  {
   "Object": "/mcs4_core_i4004_sp_board_row_reg[0]/U$1",
   "Type": "DFF",
   "Mapping": "/mcs4_core_i4004_sp_board_row_reg[0]/U$1",
   "Phase": "+",
   "User Setup object phase inversion": "+",
   "User Setup mapped object phase inversion": "+",
   "highlite": 0
  },
  {
   "Object": "/mcs4_core_ram_0_timing_recovery_x22_reg/U$1",
   "Type": "DFF",
   "Mapping": "/mcs4_core_ram_0_timing_recovery_x22_reg/U$1",
   "Phase": "+",
   "User Setup object phase inversion": "+",
   "User Setup mapped object phase inversion": "+",
   "highlite": 0
  },
  {
   "Object": "/mcs4_core_rom_0_timing_recovery_a12_reg/U$1",
   "Type": "DFF",
   "Mapping": "/mcs4_core_rom_0_timing_recovery_a12_reg/U$1",
   "Phase": "+",
   "User Setup object phase inversion": "+",
   "User Setup mapped object phase inversion": "+",
   "highlite": 0
  },
  {
   "Object": "/mcs4_core_shiftreg_cp_delay_reg[0]/U$1",
   "Type": "DFF",
   "Mapping": "/mcs4_core_shiftreg_cp_delay_reg[0]/U$1",
   "Phase": "+",
   "User Setup object phase inversion": "+",
   "User Setup mapped object phase inversion": "+",
   "highlite": 0
  },
  {
   "Object": "/mcs4_core_i4004_tio_board_L_reg/U$1",
   "Type": "DFF",
   "Mapping": "/mcs4_core_i4004_tio_board_L_reg/U$1",
   "Phase": "+",
   "User Setup object phase inversion": "+",
   "User Setup mapped object phase inversion": "+",
   "highlite": 0
  },
  {
   "Object": "/mcs4_core_i4004_sp_board_row_reg[1]/U$1",
   "Type": "DFF",
   "Mapping": "/mcs4_core_i4004_sp_board_row_reg[1]/U$1",
   "Phase": "+",
   "User Setup object phase inversion": "+",
   "User Setup mapped object phase inversion": "+",
   "highlite": 0
  },
  {
   "Object": "/mcs4_core_i4004_tio_board_timing_generator_a32_reg/U$1",
   "Type": "DFF",
   "Mapping": "/mcs4_core_i4004_tio_board_timing_generator_a32_reg/U$1",
   "Phase": "+",
   "User Setup object phase inversion": "+",
   "User Setup mapped object phase inversion": "+",
   "highlite": 0
  },
  {
   "Object": "/mcs4_core_i4004_tio_board_timing_generator_a12_reg/U$1",
   "Type": "DFF",
   "Mapping": "/mcs4_core_i4004_tio_board_timing_generator_a12_reg/U$1",
   "Phase": "+",
   "User Setup object phase inversion": "+",
   "User Setup mapped object phase inversion": "+",
   "highlite": 0
  },
  {
   "Object": "/mcs4_core_ram_0_timing_recovery_m22_reg/U$1",
   "Type": "DFF",
   "Mapping": "/mcs4_core_ram_0_timing_recovery_m22_reg/U$1",
   "Phase": "+",
   "User Setup object phase inversion": "+",
   "User Setup mapped object phase inversion": "+",
   "highlite": 0
  },
  {
   "Object": "/mcs4_core_i4004_id_board_n0343_reg/U$1",
   "Type": "DFF",
   "Mapping": "/mcs4_core_i4004_id_board_n0343_reg/U$1",
   "Phase": "+",
   "User Setup object phase inversion": "+",
   "User Setup mapped object phase inversion": "+",
   "highlite": 0
  },
  {
   "Object": "/mcs4_core_i4004_alu_board_n0749_reg/U$1",
   "Type": "DFF",
   "Mapping": "/mcs4_core_i4004_alu_board_n0749_reg/U$1",
   "Phase": "+",
   "User Setup object phase inversion": "+",
   "User Setup mapped object phase inversion": "+",
   "highlite": 0
  },
  {
   "Object": "/mcs4_core_i4004_alu_board_n0750_reg/U$1",
   "Type": "DFF",
   "Mapping": "/mcs4_core_i4004_alu_board_n0750_reg/U$1",
   "Phase": "+",
   "User Setup object phase inversion": "+",
   "User Setup mapped object phase inversion": "+",
   "highlite": 0
  },
  {
   "Object": "/mcs4_core_i4004_alu_board_n0751_reg/U$1",
   "Type": "DFF",
   "Mapping": "/mcs4_core_i4004_alu_board_n0751_reg/U$1",
   "Phase": "+",
   "User Setup object phase inversion": "+",
   "User Setup mapped object phase inversion": "+",
   "highlite": 0
  },
  {
   "Object": "/mcs4_core_ram_0_io_reg/U$1",
   "Type": "DFF",
   "Mapping": "/mcs4_core_ram_0_io_reg/U$1",
   "Phase": "+",
   "User Setup object phase inversion": "+",
   "User Setup mapped object phase inversion": "+",
   "highlite": 0
  },
  {
   "Object": "/mcs4_core_i4004_ip_board_row_reg[0]/U$1",
   "Type": "DFF",
   "Mapping": "/mcs4_core_i4004_ip_board_row_reg[0]/U$1",
   "Phase": "+",
   "User Setup object phase inversion": "+",
   "User Setup mapped object phase inversion": "+",
   "highlite": 0
  },
  {
   "Object": "/mcs4_core_i4004_ip_board_row_reg[1]/U$1",
   "Type": "DFF",
   "Mapping": "/mcs4_core_i4004_ip_board_row_reg[1]/U$1",
   "Phase": "+",
   "User Setup object phase inversion": "+",
   "User Setup mapped object phase inversion": "+",
   "highlite": 0
  },
  {
   "Object": "/mcs4_core_i4004_tio_board_timing_generator_a22_reg/U$1",
   "Type": "DFF",
   "Mapping": "/mcs4_core_i4004_tio_board_timing_generator_a22_reg/U$1",
   "Phase": "+",
   "User Setup object phase inversion": "+",
   "User Setup mapped object phase inversion": "+",
   "highlite": 0
  },
  {
   "Object": "/mcs4_core_i4004_tio_board_timing_generator_m22_reg/U$1",
   "Type": "DFF",
   "Mapping": "/mcs4_core_i4004_tio_board_timing_generator_m22_reg/U$1",
   "Phase": "+",
   "User Setup object phase inversion": "+",
   "User Setup mapped object phase inversion": "+",
   "highlite": 0
  },
  {
   "Object": "/mcs4_core_i4004_sp_board_row_reg[2]/U$1",
   "Type": "DFF",
   "Mapping": "/mcs4_core_i4004_sp_board_row_reg[2]/U$1",
   "Phase": "+",
   "User Setup object phase inversion": "+",
   "User Setup mapped object phase inversion": "+",
   "highlite": 0
  },
  {
   "Object": "/mcs4_core_i4004_tio_board_poc_reg/U$1",
   "Type": "DFF",
   "Mapping": "/mcs4_core_i4004_tio_board_poc_reg/U$1",
   "Phase": "+",
   "User Setup object phase inversion": "+",
   "User Setup mapped object phase inversion": "+",
   "highlite": 0
  },
  {
   "Object": "/mcs4_core_i4004_id_board_opa_reg[0]/U$1",
   "Type": "DFF",
   "Mapping": "/mcs4_core_i4004_id_board_opa_reg[0]/U$1",
   "Phase": "+",
   "User Setup object phase inversion": "+",
   "User Setup mapped object phase inversion": "+",
   "highlite": 0
  },
  {
   "Object": "/mcs4_core_i4004_tio_board_timing_generator_x32_reg/U$1",
   "Type": "DFF",
   "Mapping": "/mcs4_core_i4004_tio_board_timing_generator_x32_reg/U$1",
   "Phase": "+",
   "User Setup object phase inversion": "+",
   "User Setup mapped object phase inversion": "+",
   "highlite": 0
  },
  {
   "Object": "/mcs4_core_i4004_tio_board_timing_generator_x12_reg/U$1",
   "Type": "DFF",
   "Mapping": "/mcs4_core_i4004_tio_board_timing_generator_x12_reg/U$1",
   "Phase": "+",
   "User Setup object phase inversion": "+",
   "User Setup mapped object phase inversion": "+",
   "highlite": 0
  },
  {
   "Object": "/mcs4_core_i4004_tio_board_timing_generator_m12_reg/U$1",
   "Type": "DFF",
   "Mapping": "/mcs4_core_i4004_tio_board_timing_generator_m12_reg/U$1",
   "Phase": "+",
   "User Setup object phase inversion": "+",
   "User Setup mapped object phase inversion": "+",
   "highlite": 0
  }
 ],
 "cols": [
  {
   "key": "Object"
  },
  {
   "key": "Type"
  },
  {
   "key": "Mapping"
  },
  {
   "key": "Phase"
  },
  {
   "key": "User Setup object phase inversion"
  },
  {
   "key": "User Setup mapped object phase inversion"
  }
 ],
 "sort": [
  "-highlite"
 ]
}